[{"articles":[[1990,13],[1991,13],[1992,11],[1993,11],[1994,10],[1995,84],[1996,331],[1997,12],[1998,38],[1999,84],[2000,54]],"total": 661,"name": " ACM Comput. Surv. " },
{"articles":[[2000,17]],"total": 678,"name": " ACM Crossroads " },
{"articles":[[2000,31]],"total": 709,"name": " ACM Journal of Computer Documentation " },
{"articles":[[1996,4],[1997,5],[1998,9],[1999,8],[2000,17]],"total": 752,"name": " ACM Journal of Experimental Algorithmics " },
{"articles":[[2000,26]],"total": 778,"name": " ACM SIGAPL APL Quote Quad " },
{"articles":[[1999,1],[2000,2]],"total": 781,"name": " ACM SIGMOD Anthology " },
{"articles":[[1999,64],[2000,74]],"total": 919,"name": " ACM SIGMOD Digital Review " },
{"articles":[[1999,2],[2000,2]],"total": 923,"name": " ACM SIGMOD Digital Symposium Collection " },
{"articles":[[2000,173]],"total": 1096,"name": " ACM SIGSOFT Software Engineering Notes " },
{"articles":[[1993,14],[1994,28],[1995,26],[1996,33],[1997,39],[1998,30]],"total": 1266,"name": " ACM StandardView " },
{"articles":[[2000,12]],"total": 1278,"name": " ACM Trans. Comput. Log. " },
{"articles":[[1990,14],[1991,17],[1992,14],[1993,15],[1994,14],[1995,12],[1996,13],[1997,14],[1998,11],[1999,9],[2000,12]],"total": 1423,"name": " ACM Trans. Comput. Syst. " },
{"articles":[[1994,13],[1995,14],[1996,12],[1997,13],[1998,10],[1999,14],[2000,20]],"total": 1519,"name": " ACM Trans. Comput.-Hum. Interact. " },
{"articles":[[1990,20],[1991,23],[1992,21],[1993,19],[1994,17],[1995,13],[1996,14],[1997,13],[1998,12],[1999,13],[2000,12]],"total": 1696,"name": " ACM Trans. Database Syst. " },
{"articles":[[1996,20],[1997,19],[1998,29],[1999,17],[2000,35]],"total": 1816,"name": " ACM Trans. Design Autom. Electr. Syst. " },
{"articles":[[1990,21],[1991,16],[1992,19],[1993,15],[1994,17],[1995,15],[1996,15],[1997,14],[1998,12],[1999,14],[2000,13]],"total": 1987,"name": " ACM Trans. Graph. " },
{"articles":[[1990,15],[1991,18],[1992,17],[1993,17],[1994,20],[1995,17],[1996,15],[1997,14],[1998,14],[1999,16],[2000,12]],"total": 2162,"name": " ACM Trans. Inf. Syst. " },
{"articles":[[1998,5],[1999,15],[2000,12]],"total": 2194,"name": " ACM Trans. Inf. Syst. Secur. " },
{"articles":[[1990,30],[1991,41],[1992,36],[1993,35],[1994,32],[1995,30],[1996,33],[1997,30],[1998,29],[1999,28],[2000,32]],"total": 2550,"name": " ACM Trans. Math. Softw. " },
{"articles":[[1991,15],[1992,14],[1993,19],[1994,17],[1995,13],[1996,13],[1997,20],[1998,18],[1999,16],[2000,16]],"total": 2711,"name": " ACM Trans. Model. Comput. Simul. " },
{"articles":[[1990,24],[1991,25],[1992,18],[1993,29],[1994,63],[1995,37],[1996,27],[1997,35],[1998,33],[1999,32],[2000,28]],"total": 3062,"name": " ACM Trans. Program. Lang. Syst. " },
{"articles":[[1992,17],[1993,13],[1994,12],[1995,12],[1996,13],[1997,13],[1998,14],[1999,13],[2000,14]],"total": 3183,"name": " ACM Trans. Softw. Eng. Methodol. " },
{"articles":[[1990,21],[1991,13],[1992,16],[1993,7],[1994,15],[1995,17],[1996,18],[1997,12],[1998,17],[1999,30],[2000,21]],"total": 3370,"name": " Acta Cybern. " },
{"articles":[[1990,33],[1991,31],[1992,35],[1993,33],[1994,36],[1995,32],[1996,37],[1997,42],[1998,39],[1999,18],[2000,26]],"total": 3732,"name": " Acta Inf. " },
{"articles":[[1992,9],[1993,16],[1994,16],[1995,14],[1996,22],[1997,23],[1998,8],[1999,22],[2000,16]],"total": 3878,"name": " Adaptive Behaviour " },
{"articles":[[1997,6]],"total": 3884,"name": " ADS " },
{"articles":[[1993,16],[1994,25],[1995,35],[1996,44],[1997,25],[1998,41],[1999,38],[2000,38]],"total": 4146,"name": " Adv. Comput. Math. " },
{"articles":[[1990,32],[1991,42],[1992,39],[1993,45],[1994,45],[1995,39],[1996,50],[1997,52],[1998,98],[2000,61]],"total": 4649,"name": " Advanced Robotics " },
{"articles":[[1998,20],[1999,22],[2000,29]],"total": 4720,"name": " Advances in Complex Systems " },
{"articles":[[1990,10],[1991,10],[1992,12],[1993,13],[1994,10],[1995,12],[1996,11],[1997,14],[1998,15],[1999,13],[2000,14]],"total": 4854,"name": " Advances in Computers " },
{"articles":[[1990,21],[1991,12],[1992,18],[1993,7],[1994,10],[1995,8],[1996,18],[1997,17],[1998,20],[1999,21],[2000,33]],"total": 5039,"name": " AI Commun. " },
{"articles":[[1990,16],[1991,14],[1992,13],[1993,23],[1994,30],[1995,35],[1996,41],[1997,32],[1998,46],[1999,31],[2000,32]],"total": 5352,"name": " AI EDAM " },
{"articles":[[1990,19],[1991,19],[1992,16],[1993,28],[1994,5],[1995,21],[1996,35],[1997,48],[1998,34],[1999,38],[2000,29]],"total": 5644,"name": " AI in Engineering " },
{"articles":[[1990,38],[1991,49],[1992,34],[1993,35],[1994,36],[1995,42],[1996,26],[1997,48],[1998,67],[1999,43],[2000,52]],"total": 6114,"name": " AI Magazine " },
{"articles":[[1990,19],[1991,24],[1992,28],[1993,29],[1994,34],[1995,25],[1996,25],[1997,21],[1998,26],[1999,36],[2000,31]],"total": 6412,"name": " AI Soc. " },
{"articles":[[1990,33],[1991,47],[1992,57],[1993,58],[1994,60],[1995,54],[1996,68],[1997,79],[1998,73],[1999,68],[2000,73]],"total": 7082,"name": " Algorithmica " },
{"articles":[[1990,44],[1991,30],[1992,33],[1993,64],[1994,34],[1995,50],[1996,43],[1997,45],[1998,44],[1999,33],[2000,33]],"total": 7535,"name": " Ann. Math. Artif. Intell. " },
{"articles":[[1990,53],[1991,53],[1992,40],[1993,82],[1994,52],[1995,60],[1996,66],[1997,84],[1998,52],[1999,57],[2000,52]],"total": 8186,"name": " Ann. Pure Appl. Logic " },
{"articles":[[1995,13],[1996,11],[1997,33],[1998,33],[1999,24],[2000,30]],"total": 8330,"name": " Ann. Software Eng. " },
{"articles":[[1997,73],[1998,47],[1999,57],[2000,59]],"total": 8566,"name": " Annales des Télécommunications " },
{"articles":[[1995,10],[1996,8],[1997,7],[1998,11],[1999,21],[2000,22]],"total": 8645,"name": " Annals of GIS " },
{"articles":[[1993,100],[2000,77]],"total": 8822,"name": " Annals OR " },
{"articles":[[1991,1]],"total": 8823,"name": " ANSI X2H2 " },
{"articles":[[1990,2],[1991,1],[1992,1]],"total": 8827,"name": " ANSI X3H2 " },
{"articles":[[1990,12],[1991,21],[1992,22],[1993,19],[1994,21],[1995,31],[1996,33],[1997,37],[1998,16],[1999,16],[2000,29]],"total": 9084,"name": " Appl. Algebra Eng. Commun. Comput. " },
{"articles":[[1991,16],[1992,23],[1993,20],[1994,22],[1995,16],[1996,25],[1997,21],[1998,36],[1999,36],[2000,36]],"total": 9335,"name": " Appl. Intell. " },
{"articles":[[2000,164]],"total": 9499,"name": " Appl. Math. Lett. " },
{"articles":[[1990,16],[1991,23],[1992,25],[1993,24],[1994,29],[1995,29],[1996,28],[1997,36],[1998,33],[1999,33],[2000,42]],"total": 9817,"name": " Applied Artificial Intelligence " },
{"articles":[[1993,22],[1994,22],[1995,20],[1996,34],[1997,18],[1998,28],[1999,19],[2000,42]],"total": 10022,"name": " Applied Categorical Structures " },
{"articles":[[1999,126],[2000,134]],"total": 10282,"name": " Applied Mathematics and Computation " },
{"articles":[[1995,24],[1996,25],[1997,27],[1998,28],[1999,29],[2000,34]],"total": 10449,"name": " Arch. Math. Log. " },
{"articles":[[1995,48],[1996,73],[1997,78],[1998,87],[1999,108],[2000,87]],"total": 10930,"name": " Ars Comb. " },
{"articles":[[1990,66],[1991,74],[1992,78],[1993,119],[1994,82],[1995,111],[1996,111],[1997,91],[1998,100],[1999,82],[2000,82]],"total": 11926,"name": " Artif. Intell. " },
{"articles":[[1992,11],[1993,13],[1995,14],[1996,9],[1997,14],[1998,11],[1999,24],[2000,22]],"total": 12044,"name": " Artif. Intell. Law " },
{"articles":[[1990,17],[1991,17],[1992,19],[1993,23],[1994,20],[1995,25],[1996,22],[1997,17],[1998,20],[1999,19],[2000,25]],"total": 12268,"name": " Artif. Intell. Rev. " },
{"articles":[[1990,33],[1991,38],[1992,31],[1993,30],[1994,31],[1995,27],[1996,30],[1997,41],[1998,41],[1999,43],[2000,46]],"total": 12659,"name": " Artificial Intelligence in Medicine " },
{"articles":[[1994,28],[1995,15],[1997,20],[1998,23],[1999,18],[2000,25]],"total": 12788,"name": " Artificial Life " },
{"articles":[[1998,19],[1999,24],[2000,21]],"total": 12852,"name": " Aslib Proceedings " },
{"articles":[[1993,9],[1994,14],[1995,15],[1996,19],[1997,23],[1998,33],[1999,29],[2000,28]],"total": 13022,"name": " Australasian J. of Inf. Systems " },
{"articles":[[1990,16],[1991,17],[1992,16],[1993,15],[1994,16],[1995,13],[1996,16],[1997,18],[1998,15],[1999,16]],"total": 13180,"name": " Australian Computer Journal " },
{"articles":[[1994,20],[1995,17],[1996,14],[1997,25],[1998,21],[1999,20],[2000,19]],"total": 13316,"name": " Autom. Softw. Eng. " },
{"articles":[[1990,125],[1991,139],[1992,160],[1993,178],[1994,219],[1995,206],[1996,217],[1997,262],[1998,189],[1999,191],[2000,191]],"total": 15393,"name": " Automatica " },
{"articles":[[1994,6],[1995,30],[1996,23],[1997,26],[1998,25],[1999,40],[2000,45]],"total": 15588,"name": " Auton. Robots " },
{"articles":[[1998,9],[1999,19],[2000,15]],"total": 15631,"name": " Autonomous Agents and Multi-Agent Systems " },
{"articles":[[1993,40],[1994,39],[1995,37],[1996,31],[1997,28],[1998,36],[1999,38],[2000,40]],"total": 15920,"name": " Behaviour & IT " },
{"articles":[[2000,56]],"total": 15976,"name": " Bell Labs Technical Journal " },
{"articles":[[1990,14],[1991,11],[1992,15],[1993,12],[1994,11],[1995,12],[1996,12],[1997,13],[1998,12],[1999,11],[2000,9]],"total": 16108,"name": " BIAA " },
{"articles":[[1998,128],[1999,143],[2000,177]],"total": 16556,"name": " Bioinformatics " },
{"articles":[[1991,78],[1992,120],[1993,121],[1994,110],[1995,102],[1996,95],[1997,91],[1998,91],[1999,78],[2000,93]],"total": 17535,"name": " Biological Cybernetics " },
{"articles":[[1990,28],[1991,21],[1992,29],[1993,24]],"total": 17637,"name": " BIT " },
{"articles":[[2000,1]],"total": 17638,"name": " BMC Bioinformatics " },
{"articles":[[2000,39]],"total": 17677,"name": " Briefings in Bioinformatics " },
{"articles":[[1995,16],[1996,17],[1997,14],[1998,13],[1999,14],[2000,14]],"total": 17765,"name": " Bulletin of Symbolic Logic " },
{"articles":[[1990,44],[1991,33],[1992,32],[1993,36],[1994,27],[1995,26],[1996,27],[1997,25],[1998,27],[1999,28],[2000,29]],"total": 18099,"name": " Bulletin of the EATCS " },
{"articles":[[1994,7]],"total": 18106,"name": " Bulletin of the IGPL " },
{"articles":[[1997,15],[1998,19],[1999,17],[2000,24]],"total": 18181,"name": " Business Proc. Manag. Journal " },
{"articles":[[2000,2]],"total": 18183,"name": " C't Magazin für Computer Technik " },
{"articles":[[2000,22]],"total": 18205,"name": " Cartographica " },
{"articles":[[1995,4],[1996,6],[1997,5],[1998,4],[1999,11],[2000,4]],"total": 18239,"name": " Chicago J. Theor. Comput. Sci. " },
{"articles":[[1998,9],[1999,5],[2000,2]],"total": 18255,"name": " CLEI Electron. J. " },
{"articles":[[1998,22],[1999,27],[2000,24]],"total": 18328,"name": " Cluster Computing " },
{"articles":[[1999,22],[2000,34]],"total": 18384,"name": " Cognition  Technology & Work " },
{"articles":[[1990,20],[1991,17],[1992,16],[1993,23],[1994,17],[1995,15],[1996,15],[1997,14],[1998,15],[1999,21],[2000,21]],"total": 18578,"name": " Cognitive Science " },
{"articles":[[1999,6],[2000,11]],"total": 18595,"name": " Cognitive Systems Research " },
{"articles":[[1990,31],[1991,36],[1992,46],[1993,35],[1994,37],[1995,45],[1996,46],[1997,38],[1998,41],[1999,31],[2000,39]],"total": 19020,"name": " Combinatorica " },
{"articles":[[1992,32],[1993,38],[1994,41],[1995,27],[1996,34],[1997,42],[1998,45],[1999,23],[2000,41]],"total": 19343,"name": " Combinatorics  Probability & Computing " },
{"articles":[[1990,118],[1991,117],[1992,137],[1993,158],[1994,151],[1995,191],[1996,198],[1997,213],[1998,225],[1999,247],[2000,270]],"total": 21368,"name": " Commun. ACM " },
{"articles":[[2000,29]],"total": 21397,"name": " Comp. and Biomed. Research " },
{"articles":[[2000,24]],"total": 21421,"name": " Comp. in Bio. and Med. " },
{"articles":[[1998,27],[1999,47],[2000,44]],"total": 21539,"name": " Comp. Opt. and Appl. " },
{"articles":[[1995,36],[1996,54],[1997,69],[1998,58],[1999,46],[2000,51]],"total": 21853,"name": " Complexity " },
{"articles":[[1995,1]],"total": 21854,"name": " Compulog Newsletter " },
{"articles":[[1991,18],[1992,24],[1993,21],[1994,19],[1995,20],[1996,24],[1997,46],[1998,54],[1999,45],[2000,38]],"total": 22163,"name": " Comput. Geom. " },
{"articles":[[1990,24],[1991,25],[1992,61],[1993,65],[1994,66],[1995,59],[1996,65],[1997,57],[1998,49],[1999,55],[2000,76]],"total": 22765,"name": " Comput. Graph. Forum " },
{"articles":[[1990,71],[1991,62],[1992,81],[1993,79],[1994,76],[1995,71],[1996,71],[1997,54],[1998,52],[1999,63],[2000,40]],"total": 23485,"name": " Comput. J. " },
{"articles":[[1990,17],[1991,17],[1992,18],[1993,35],[1994,17],[1995,12],[1996,17],[1997,8],[1998,11],[1999,14],[2000,7]],"total": 23658,"name": " Comput. Lang. " },
{"articles":[[1990,31]],"total": 23689,"name": " Comput. Syst. Sci. Eng. " },
{"articles":[[1999,8],[2000,15]],"total": 23712,"name": " Computación y Sistemas " },
{"articles":[[1995,6],[1996,18],[1997,9],[1998,19],[1999,18],[2000,21]],"total": 23803,"name": " Computational & Mathematical Organization Theory " },
{"articles":[[1991,15],[1992,17],[1993,18],[1994,20],[1995,16],[1997,20],[1998,16],[1999,18],[2000,11]],"total": 23954,"name": " Computational Complexity " },
{"articles":[[1990,20],[1991,15],[1992,48],[1993,12],[1994,48],[1995,31],[1996,28],[1997,21],[1998,21],[1999,18],[2000,28]],"total": 24244,"name": " Computational Intelligence " },
{"articles":[[1990,14],[1991,13],[1992,16],[1993,22],[1994,29],[1995,20],[1996,22],[1997,21],[1998,22],[1999,21],[2000,21]],"total": 24465,"name": " Computational Linguistics " },
{"articles":[[1990,40],[1991,41],[1992,38],[1993,37],[1994,39],[1995,55],[1996,51],[1997,66],[1998,45],[1999,59],[2000,41]],"total": 24977,"name": " Computer Aided Geometric Design " },
{"articles":[[1990,59],[1991,81],[1992,92],[1993,112],[1994,102],[1995,89],[1996,76],[1997,93]],"total": 25681,"name": " Computer Applications in the Biosciences " },
{"articles":[[1995,37],[1996,16],[1997,23],[1998,23],[1999,26],[2000,20]],"total": 25826,"name": " Computer Communication Review " },
{"articles":[[1990,77],[1991,66],[1992,73],[1993,88],[1994,90],[1995,103],[1996,117],[1997,120],[1998,157],[1999,183],[2000,175]],"total": 27075,"name": " Computer Communications " },
{"articles":[[2000,69]],"total": 27144,"name": " Computer Methods and Programs in Biomedicine " },
{"articles":[[1996,58],[1997,62],[1998,248],[1999,166],[2000,168]],"total": 27846,"name": " Computer Networks " },
{"articles":[[1992,8],[1994,16],[1995,6],[1997,52],[1998,13]],"total": 27941,"name": " Computer Networks and ISBN Systems " },
{"articles":[[1990,106],[1991,101],[1992,94],[1993,96],[1994,118],[1995,106],[1996,83],[1997,32]],"total": 28677,"name": " Computer Networks and ISDN Systems " },
{"articles":[[1990,17],[1991,25],[1992,22],[1993,17],[1994,15],[1995,11],[1996,18],[1998,13],[1999,18],[2000,18]],"total": 28851,"name": " Computer Science Education " },
{"articles":[[1993,19],[1994,20],[1995,17],[1996,15],[1997,15],[1998,22],[1999,19],[2000,20]],"total": 28998,"name": " Computer Speech & Language " },
{"articles":[[1996,33],[1997,24],[1998,29]],"total": 29084,"name": " Computer Standards & Interfaces " },
{"articles":[[1992,8],[1993,4],[1994,31],[1995,14],[1996,18],[1997,18],[1998,15],[1999,18],[2000,20]],"total": 29230,"name": " Computer Supported Cooperative Work " },
{"articles":[[1990,87]],"total": 29317,"name": " Computer Vision  Graphics  and Image Processing " },
{"articles":[[1995,58],[1996,66],[1997,102],[1998,103],[1999,87],[2000,71]],"total": 29804,"name": " Computer Vision and Image Understanding " },
{"articles":[[1990,104],[1991,83],[1992,76],[1993,89],[1994,99],[1995,80],[1996,87],[1997,79],[1998,105],[1999,69],[2000,76]],"total": 30751,"name": " Computer-Aided Design " },
{"articles":[[1990,53],[1991,56],[1992,51],[1993,61],[1994,55],[1995,58],[1996,51],[1997,48],[1998,57],[1999,51],[2000,70]],"total": 31362,"name": " Computers & Chemistry " },
{"articles":[[1996,52],[1997,52],[1998,53],[1999,38],[2000,61]],"total": 31618,"name": " Computers & Education " },
{"articles":[[2000,6]],"total": 31624,"name": " Computers & Electrical Engineering " },
{"articles":[[1990,64],[1991,73],[1992,65],[1993,92],[1994,96],[1995,84],[1996,91],[1997,85],[1998,70],[1999,80],[2000,81]],"total": 32505,"name": " Computers & Graphics " },
{"articles":[[1990,62],[1991,81],[1992,74],[1993,75],[1994,99],[1995,96],[1996,105],[1997,103],[1998,96],[1999,88],[2000,88]],"total": 33472,"name": " Computers & OR " },
{"articles":[[1990,69],[1991,63],[1992,59],[1993,60],[1994,57],[1995,52],[1996,68],[1997,56],[1998,72],[1999,60],[2000,192]],"total": 34280,"name": " Computers & Security " },
{"articles":[[1994,1],[1995,30],[1996,31],[1997,31],[1998,33],[1999,31],[2000,29]],"total": 34466,"name": " Computers and Artificial Intelligence " },
{"articles":[[1990,38],[1991,34],[1992,26],[1993,46],[1994,42],[1995,39],[1996,31],[1997,31],[1998,23],[1999,31],[2000,38]],"total": 34845,"name": " Computers and the Humanities " },
{"articles":[[1990,72],[1991,41],[1992,63],[1993,55],[1994,53],[1995,45],[1996,45],[1997,48],[1998,43],[1999,46],[2000,44]],"total": 35400,"name": " Computing " },
{"articles":[[1990,11],[1991,14],[1992,14],[1993,13],[1994,16],[1995,12],[1996,18]],"total": 35498,"name": " Computing Systems " },
{"articles":[[1990,12],[1991,48],[1992,32],[1993,35],[1994,33],[1995,39],[1996,41],[1997,83],[1998,79],[1999,50],[2000,81]],"total": 36031,"name": " Concurrency - Practice and Experience " },
{"articles":[[1990,1]],"total": 36032,"name": " Concurrency and Computation: Practice and Experience " },
{"articles":[[1994,27],[1995,11],[1996,22],[1997,20],[1998,19],[1999,16],[2000,14]],"total": 36161,"name": " Connect. Sci. " },
{"articles":[[1996,5],[1997,30],[1998,22],[1999,18],[2000,16]],"total": 36252,"name": " Constraints " },
{"articles":[[1993,18],[1994,250],[1995,253],[1996,235],[1997,188],[1998,324],[1999,321],[2000,478]],"total": 38319,"name": " CoRR " },
{"articles":[[1990,30],[1991,26],[1992,19],[1993,23],[1994,24],[1995,32],[1996,31],[1997,27],[1998,27],[1999,27],[2000,29]],"total": 38614,"name": " Cryptologia " },
{"articles":[[1991,58],[1992,47],[1993,41],[1994,46],[1995,44],[1996,46],[1997,40]],"total": 38936,"name": " CVGIP: Graphical Model and Image Processing " },
{"articles":[[1991,55],[1992,52]],"total": 39043,"name": " CVGIP: Image Understanding " },
{"articles":[[1998,26],[1999,26],[2000,25]],"total": 39120,"name": " Cybernetics and Human Knowing " },
{"articles":[[1997,39],[1998,45],[1999,42],[2000,43]],"total": 39289,"name": " Cybernetics and Systems " },
{"articles":[[1998,54],[1999,73],[2000,114]],"total": 39530,"name": " Cyberpsy.  Behavior  and Soc. Networking " },
{"articles":[[1995,19],[1996,51],[1997,58],[1998,51],[1999,54],[2000,49]],"total": 39812,"name": " D-Lib Magazine " },
{"articles":[[1990,16],[1991,13],[1992,25],[1993,17],[1994,28],[1995,30],[1996,54],[1997,44],[1998,44],[1999,30],[2000,21]],"total": 40134,"name": " DATA BASE " },
{"articles":[[1990,20],[1991,38],[1992,25],[1993,26],[1994,30],[1995,32],[1996,38],[1997,47],[1998,60],[1999,40],[2000,52]],"total": 40542,"name": " Data Knowl. Eng. " },
{"articles":[[1997,18],[1998,17],[1999,17],[2000,14]],"total": 40608,"name": " Data Min. Knowl. Discov. " },
{"articles":[[1998,5],[1999,2]],"total": 40615,"name": " Data Quality Journal " },
{"articles":[[1991,45],[1992,65],[1993,52],[1997,45],[1998,46],[1999,32],[2000,20]],"total": 40920,"name": " Datenbank Rundbrief " },
{"articles":[[1999,146],[2000,140]],"total": 41206,"name": " Datenschutz und Datensicherheit " },
{"articles":[[2000,36]],"total": 41242,"name": " Decision Sciences " },
{"articles":[[1993,23],[1994,67],[1995,79],[1996,74],[1997,68],[1998,64],[1999,68],[2000,78]],"total": 41763,"name": " Decision Support Systems " },
{"articles":[[1991,26],[1992,28],[1993,30],[1994,27],[1995,37],[1996,69],[1997,63],[1998,67],[1999,68],[2000,49]],"total": 42227,"name": " Des. Codes Cryptography " },
{"articles":[[1996,14],[1997,15],[1998,14],[1999,12],[2000,24]],"total": 42306,"name": " Design Autom. for Emb. Sys. " },
{"articles":[[1997,24],[1998,30],[1999,25],[2000,20]],"total": 42405,"name": " Digital Creativity " },
{"articles":[[1991,34],[1992,31],[1996,26],[1997,28],[1998,24],[1999,24],[2000,23]],"total": 42595,"name": " Digital Signal Processing " },
{"articles":[[1997,1]],"total": 42596,"name": " Digital System Research Center Report " },
{"articles":[[1991,35],[1992,45],[1993,42],[1994,27],[1995,36],[1996,35],[1997,13],[1998,23]],"total": 42852,"name": " Digital Technical Journal " },
{"articles":[[1990,35],[1991,36],[1992,53],[1993,53],[1994,57],[1995,71],[1996,49],[1997,56],[1998,75],[1999,80],[2000,84]],"total": 43501,"name": " Discrete & Computational Geometry " },
{"articles":[[1990,93],[1991,105],[1992,142],[1993,152],[1994,178],[1995,173],[1996,149],[1997,189],[1998,167],[1999,162],[2000,153]],"total": 45164,"name": " Discrete Applied Mathematics " },
{"articles":[[1991,8],[1992,12],[1993,22],[1994,16],[1995,16],[1996,18],[1997,15],[1998,16],[1999,20],[2000,14]],"total": 45321,"name": " Discrete Event Dynamic Systems " },
{"articles":[[1990,254],[1991,343],[1992,354],[1993,366],[1994,378],[1995,302],[1996,432],[1997,413],[1998,399],[1999,380],[2000,363]],"total": 49305,"name": " Discrete Mathematics " },
{"articles":[[1997,16],[1998,6],[1999,15],[2000,6]],"total": 49348,"name": " Discrete Mathematics & Theoretical Computer Science " },
{"articles":[[1995,18],[1996,18],[1997,22],[1998,22],[1999,22],[2000,26]],"total": 49476,"name": " Discussiones Mathematicae Graph Theory " },
{"articles":[[1993,19],[1994,16],[1995,14],[1996,15],[1997,12],[1998,13],[1999,18],[2000,15]],"total": 49598,"name": " Distributed and Parallel Databases " },
{"articles":[[1990,9],[1991,23],[1992,14],[1993,22],[1994,15],[1995,22],[1996,7],[1997,16],[1998,9],[1999,17],[2000,16]],"total": 49768,"name": " Distributed Computing " },
{"articles":[[1993,12],[1994,21],[1995,19],[1996,26],[1997,23],[1998,21],[1999,17]],"total": 49907,"name": " Distributed Systems Engineering " },
{"articles":[[1996,18],[1997,32],[1998,24],[1999,32],[2000,33]],"total": 50046,"name": " EAIT " },
{"articles":[[1998,5],[1999,25],[2000,20]],"total": 50096,"name": " Education for Information " },
{"articles":[[1998,14],[1999,85],[2000,106]],"total": 50301,"name": " Educational Technology & Society " },
{"articles":[[2000,22]],"total": 50323,"name": " Egyptian Computer Science Journal " },
{"articles":[[2000,37]],"total": 50360,"name": " EJIS " },
{"articles":[[1994,14],[1995,30],[1996,62],[1997,54],[1998,48],[1999,46],[2000,66]],"total": 50680,"name": " Electr. J. Comb. " },
{"articles":[[1995,64],[1996,56],[1997,76],[1998,127],[1999,205],[2000,169]],"total": 51377,"name": " Electr. Notes Theor. Comput. Sci. " },
{"articles":[[1997,6],[1998,10],[1999,19],[2000,15]],"total": 51427,"name": " Electron. Trans. Artif. Intell. " },
{"articles":[[1994,27],[1995,63],[1996,67],[1997,61],[1998,78],[1999,48],[2000,91]],"total": 51862,"name": " Electronic Colloquium on Computational Complexity (ECCC) " },
{"articles":[[1991,4],[1992,10],[1994,17],[1995,37],[1996,14],[1997,46],[1998,56],[1999,45],[2000,43]],"total": 52134,"name": " Electronic Markets " },
{"articles":[[1992,1]],"total": 52135,"name": " Electronic Networking: Research  Applications and Policy " },
{"articles":[[1999,100],[2000,97]],"total": 52332,"name": " Electronic Notes in Discrete Mathematics " },
{"articles":[[1990,17],[1991,17],[1992,16],[1993,45],[1994,19],[1995,3]],"total": 52449,"name": " Electronic Publishing " },
{"articles":[[1990,37],[1991,30],[1992,23],[1993,30],[1994,22]],"total": 52591,"name": " Elektronische Informationsverarbeitung und Kybernetik " },
{"articles":[[1992,15],[1993,5],[1994,11],[1995,5],[1996,24],[1997,1],[1998,3],[1999,5],[2000,3]],"total": 52663,"name": " EMISA Forum " },
{"articles":[[1996,12],[1997,29],[1998,19],[1999,20],[2000,22]],"total": 52765,"name": " Empirical Software Engineering " },
{"articles":[[1999,30],[2000,24]],"total": 52819,"name": " Eng. Comput. (Lond.) " },
{"articles":[[1999,16],[2000,12]],"total": 52847,"name": " Entropy " },
{"articles":[[1998,20],[1999,43],[2000,74]],"total": 52984,"name": " Environmental Modelling and Software " },
{"articles":[[1992,51],[1993,62],[1994,60],[1995,53],[1996,66],[1997,81],[1998,95],[1999,72],[2000,97]],"total": 53621,"name": " Eur. J. Comb. " },
{"articles":[[1997,50],[1998,44],[1999,396],[2000,396]],"total": 54507,"name": " European Journal of Operational Research " },
{"articles":[[1990,80],[1991,72],[1992,69],[1993,71],[1994,74],[1995,61],[1996,57],[1997,64],[1998,53],[1999,57],[2000,65]],"total": 55230,"name": " European Transactions on Telecommunications " },
{"articles":[[1993,16],[1994,18],[1995,18],[1996,17],[1997,17],[1998,18],[1999,19],[2000,19]],"total": 55372,"name": " Evolutionary Computation " },
{"articles":[[1992,24],[1993,20],[1994,24],[1995,26],[1996,24],[1997,32],[1998,25],[1999,31],[2000,49]],"total": 55627,"name": " Experimental Mathematics " },
{"articles":[[1996,4],[1997,16],[1998,15],[1999,24],[2000,24]],"total": 55710,"name": " Finance and Stochastics " },
{"articles":[[1996,40],[1997,65],[1998,67],[1999,66],[2000,91]],"total": 56039,"name": " First Monday " },
{"articles":[[1990,16],[1991,13],[1992,30],[1993,21],[1994,37],[1995,32],[1996,31],[1997,24],[1998,31],[1999,30],[2000,36]],"total": 56340,"name": " Formal Asp. Comput. " },
{"articles":[[1992,12],[1993,19],[1994,21],[1995,20],[1996,18],[1997,24],[1998,18],[1999,23],[2000,21]],"total": 56516,"name": " Formal Methods in System Design " },
{"articles":[[1990,1],[1991,50],[1992,36],[1993,38],[1994,36],[1995,52],[1996,96],[1997,87],[1998,71],[1999,83],[2000,68]],"total": 57134,"name": " Fundam. Inform. " },
{"articles":[[1992,37],[1993,33],[1994,48],[1995,54],[1996,24],[1997,36],[1998,62],[1999,90],[2000,85]],"total": 57603,"name": " Future Generation Comp. Syst. " },
{"articles":[[2000,67]],"total": 57670,"name": " Games and Economic Behavior " },
{"articles":[[2000,19]],"total": 57689,"name": " Genetic Programming and Evolvable Machines " },
{"articles":[[1997,14],[1998,19],[1999,16],[2000,24]],"total": 57762,"name": " GeoInformatica " },
{"articles":[[1993,20],[1994,36],[1995,24]],"total": 57842,"name": " GI Datenbank Rundbrief " },
{"articles":[[1998,8],[1999,23],[2000,16]],"total": 57889,"name": " Grammars " },
{"articles":[[2000,22]],"total": 57911,"name": " Graphical Models " },
{"articles":[[1998,30],[1999,19]],"total": 57960,"name": " Graphical Models and Image Processing " },
{"articles":[[1990,37],[1991,36],[1992,40],[1993,40],[1994,48],[1995,38],[1996,33],[1997,36],[1998,30],[1999,41],[2000,37]],"total": 58376,"name": " Graphs and Combinatorics " },
{"articles":[[1990,1],[1991,3],[1993,3],[1994,1],[1995,1]],"total": 58385,"name": " GTE Laboratories Incorporated " },
{"articles":[[1998,12],[1999,19],[2000,28]],"total": 58444,"name": " Higher-Order and Symbolic Computation " },
{"articles":[[1994,19],[1995,24],[1996,22],[1997,16],[1998,15],[1999,21],[2000,30]],"total": 58591,"name": " History and Computing " },
{"articles":[[1994,52],[1995,40],[1996,54],[1997,49],[1998,57],[1999,75],[2000,77]],"total": 58995,"name": " HMD - Praxis Wirtschaftsinform. " },
{"articles":[[1995,61],[1996,56],[1997,56],[1998,55],[1999,55],[2000,48]],"total": 59326,"name": " Human Factors " },
{"articles":[[1990,12],[1991,13],[1992,12],[1993,14],[1994,13],[1995,11],[1996,14],[1997,13],[1998,13],[1999,11],[2000,11]],"total": 59463,"name": " Human-Computer Interaction " },
{"articles":[[1990,14],[1991,10],[1992,9],[1993,9],[1994,11]],"total": 59516,"name": " Hypermedia " },
{"articles":[[2000,189]],"total": 59705,"name": " I. J. Bifurcation and Chaos " },
{"articles":[[1999,19],[2000,70]],"total": 59794,"name": " I. J. Medical Informatics " },
{"articles":[[1990,42],[1994,41],[1995,41],[1996,35],[1997,50],[1998,86],[1999,84],[2000,76]],"total": 60249,"name": " I. J. Robotic Res. " },
{"articles":[[1996,16],[1997,15],[1998,26],[1999,24],[2000,68]],"total": 60398,"name": " IACR Cryptology ePrint Archive " },
{"articles":[[1990,13],[1991,59],[1992,63],[1993,43],[1994,47],[1995,45],[1996,41],[1997,51],[1998,61],[1999,54],[2000,64]],"total": 60939,"name": " IBM Journal of Research and Development " },
{"articles":[[1990,36],[1991,36],[1992,44],[1993,33],[1994,27],[1995,38],[1996,38],[1997,30],[1998,34],[1999,41],[2000,62]],"total": 61358,"name": " IBM Systems Journal " },
{"articles":[[1998,29],[1999,32],[2000,25]],"total": 61444,"name": " IEE Proceedings - Software " },
{"articles":[[1995,35],[1996,49],[1997,41],[1998,43],[1999,42],[2000,39]],"total": 61693,"name": " IEEE Annals of the History of Computing " },
{"articles":[[1997,52],[1998,103],[1999,104],[2000,132]],"total": 62084,"name": " IEEE Communications Letters " },
{"articles":[[1998,6],[1999,16],[2000,15]],"total": 62121,"name": " IEEE Communications Surveys and Tutorials " },
{"articles":[[1990,87],[1991,106],[1992,87],[1993,77],[1994,94],[1995,165],[1996,129],[1997,174],[1998,182],[1999,174],[2000,152]],"total": 63548,"name": " IEEE Computer " },
{"articles":[[1996,82],[1997,81],[1998,85],[1999,84],[2000,90]],"total": 63970,"name": " IEEE Computer Graphics and Applications " },
{"articles":[[1997,41],[1998,53],[1999,49],[2000,50]],"total": 64163,"name": " IEEE Concurrency " },
{"articles":[[1990,41],[1991,34],[1992,17],[1993,46],[1994,34],[1995,27],[1996,30],[1997,25],[1998,33],[1999,35],[2000,35]],"total": 64520,"name": " IEEE Data Eng. Bull. " },
{"articles":[[1990,54],[1991,55],[1992,50],[1993,56],[1994,51],[1995,70],[1996,67],[1997,77],[1998,75],[1999,77],[2000,76]],"total": 65228,"name": " IEEE Design & Test of Computers " },
{"articles":[[2000,13]],"total": 65241,"name": " IEEE Distributed Systems Online " },
{"articles":[[1990,74],[1991,81],[1992,84],[1993,96],[1994,88],[1995,77],[1996,104],[1997,90]],"total": 65935,"name": " IEEE Expert " },
{"articles":[[1998,89],[1999,11],[2000,83]],"total": 66118,"name": " IEEE Intelligent Systems " },
{"articles":[[1997,98],[1998,94],[1999,85],[2000,95]],"total": 66490,"name": " IEEE Internet Computing " },
{"articles":[[1990,172],[1991,157],[1992,140],[1993,135],[1994,172],[1995,151],[1996,162],[1997,140],[1998,147],[1999,171],[2000,227]],"total": 68264,"name": " IEEE Journal on Selected Areas in Communications " },
{"articles":[[1995,8],[1996,8],[2000,89]],"total": 68369,"name": " IEEE Micro " },
{"articles":[[1994,45],[1995,41],[1996,53],[1997,48],[1998,59],[1999,56],[2000,77]],"total": 68748,"name": " IEEE MultiMedia " },
{"articles":[[1993,34],[1994,41],[1995,30],[1996,34]],"total": 68887,"name": " IEEE P&DT " },
{"articles":[[1994,20],[1995,33],[1996,32],[1997,35],[1998,40],[1999,39],[2000,47]],"total": 69133,"name": " IEEE Personal Commun. " },
{"articles":[[1994,13],[1995,15],[1996,18],[1997,19],[1998,24],[1999,21],[2000,21]],"total": 69264,"name": " IEEE Robot. Automat. Mag. " },
{"articles":[[1990,60],[1991,48],[1992,44],[1993,24],[1994,125],[1995,125],[1996,122],[1997,107],[1998,138],[1999,124],[2000,132]],"total": 70313,"name": " IEEE Software " },
{"articles":[[1993,25],[1994,31],[1995,48],[1996,46],[1997,54],[1998,55],[1999,77],[2000,72]],"total": 70721,"name": " IEEE T. Fuzzy Systems " },
{"articles":[[1991,124],[1992,134],[1993,136],[1994,136],[1995,152],[1996,137],[1997,148],[1998,197],[1999,267],[2000,257]],"total": 72409,"name": " IEEE T. Geoscience and Remote Sensing " },
{"articles":[[1998,259],[1999,257],[2000,229]],"total": 73154,"name": " IEEE T. Instrumentation and Measurement " },
{"articles":[[1990,86],[1991,96],[1992,75],[1993,91],[1994,75],[1995,99],[1996,89],[1997,87],[1998,100],[1999,112],[2000,94]],"total": 74158,"name": " IEEE T. Robotics and Automation " },
{"articles":[[2000,235]],"total": 74393,"name": " IEEE T. Vehicular Technology " },
{"articles":[[1997,18],[1998,18],[1999,20],[2000,15]],"total": 74464,"name": " IEEE Technol. Soc. Mag. " },
{"articles":[[1990,264]],"total": 74728,"name": " IEEE Trans. Acoustics  Speech  and Signal Processing " },
{"articles":[[1999,374],[2000,361]],"total": 75463,"name": " IEEE Trans. Automat. Contr. " },
{"articles":[[2000,201]],"total": 75664,"name": " IEEE Trans. Biomed. Engineering " },
{"articles":[[1991,36],[1992,39],[1993,47],[1994,54],[1995,69],[1996,65],[1997,98],[1998,94],[1999,112],[2000,139]],"total": 76417,"name": " IEEE Trans. Circuits Syst. Video Techn. " },
{"articles":[[1990,175],[1991,161],[1992,180],[1993,173],[1994,175],[1995,166],[1996,164],[1997,152],[1998,136],[1999,119],[2000,128]],"total": 78146,"name": " IEEE Trans. Computers " },
{"articles":[[1999,169],[2000,159]],"total": 78474,"name": " IEEE Trans. Consumer Electronics " },
{"articles":[[1993,28],[1994,50],[1995,47],[1996,80],[1997,45],[1998,69],[1999,74],[2000,92]],"total": 78959,"name": " IEEE Trans. Contr. Sys. Techn. " },
{"articles":[[2000,72]],"total": 79031,"name": " IEEE Trans. Education " },
{"articles":[[1997,28],[1998,15],[1999,28],[2000,33]],"total": 79135,"name": " IEEE Trans. Evolutionary Computation " },
{"articles":[[1990,34],[1991,56],[1992,53],[1993,94],[1994,84],[1995,81],[1996,90],[1997,81],[1998,70],[1999,72],[2000,65]],"total": 79915,"name": " IEEE Trans. Knowl. Data Eng. " },
{"articles":[[1993,94],[1994,73],[1995,79],[1996,85],[1997,97],[1998,115],[1999,111],[2000,118]],"total": 80687,"name": " IEEE Trans. Med. Imaging " },
{"articles":[[2000,144]],"total": 80831,"name": " IEEE Trans. Neural Netw. Learning Syst. " },
{"articles":[[1990,132],[1991,157],[1992,139],[1993,192],[1994,148],[1995,152],[1996,149],[1997,135],[1998,122],[1999,152],[2000,140]],"total": 82449,"name": " IEEE Trans. on CAD of Integrated Circuits and Systems " },
{"articles":[[1990,45],[1991,46],[1992,68],[1993,120],[1994,127],[1995,126],[1996,116],[1997,111],[1998,101],[1999,95],[2000,93]],"total": 83497,"name": " IEEE Trans. Parallel Distrib. Syst. " },
{"articles":[[1990,122],[1991,116],[1992,112],[1993,135],[1994,147],[1995,140],[1996,143],[1997,138],[1998,140],[1999,140],[2000,134]],"total": 84964,"name": " IEEE Trans. Pattern Anal. Mach. Intell. " },
{"articles":[[1990,131],[1991,109],[1992,91],[1993,92],[1994,80],[1995,89],[1996,70],[1997,59],[1998,72],[1999,63],[2000,80]],"total": 85900,"name": " IEEE Trans. Software Eng. " },
{"articles":[[1995,32],[1996,35],[1997,30],[1998,28],[1999,26],[2000,29]],"total": 86080,"name": " IEEE Trans. Vis. Comput. Graph. " },
{"articles":[[1993,59],[1994,54],[1995,48],[1996,46],[1997,48],[1998,82],[1999,56],[2000,85]],"total": 86558,"name": " IEEE Trans. VLSI Syst. " },
{"articles":[[1990,293],[1991,242],[1992,209],[1993,229],[1994,392],[1995,399],[1996,234],[1997,230],[1998,224],[1999,248],[2000,257]],"total": 89515,"name": " IEEE Transactions on Communications " },
{"articles":[[1992,55],[1993,52],[1994,78],[1995,168],[1996,174],[1997,162],[1998,172],[1999,189],[2000,213]],"total": 90778,"name": " IEEE Transactions on Image Processing " },
{"articles":[[1997,110],[1998,124],[1999,150],[2000,157]],"total": 91319,"name": " IEEE Transactions on Industrial Electronics " },
{"articles":[[1997,29],[1998,35],[1999,33],[2000,41]],"total": 91457,"name": " IEEE Transactions on Information Technology in Biomedicine " },
{"articles":[[1990,199],[1991,251],[1992,225],[1993,244],[1994,257],[1995,246],[1996,255],[1997,245],[1998,283],[1999,302],[2000,277]],"total": 94241,"name": " IEEE Transactions on Information Theory " },
{"articles":[[2000,20]],"total": 94261,"name": " IEEE Transactions on Intelligent Transportation Systems " },
{"articles":[[1999,27],[2000,21]],"total": 94309,"name": " IEEE Transactions on Multimedia " },
{"articles":[[1990,35],[1991,74],[1992,103],[1993,106],[1994,103],[1995,173],[1996,166],[1997,157],[1998,149],[1999,164]],"total": 95539,"name": " IEEE Transactions on Neural Networks " },
{"articles":[[1996,107],[2000,48]],"total": 95694,"name": " IEEE Transactions on Reliability " },
{"articles":[[1991,382],[1992,369],[1993,386],[1994,446],[1995,378],[1996,373],[1997,341],[1998,390],[1999,37],[2000,400]],"total": 99196,"name": " IEEE Transactions on Signal Processing " },
{"articles":[[1993,48],[1994,73],[1995,53],[1996,51],[1997,60],[1998,57],[1999,74],[2000,80]],"total": 99692,"name": " IEEE Transactions on Speech and Audio Processing " },
{"articles":[[1990,144],[1991,159],[1992,141],[1993,160],[1994,30],[1995,165]],"total": 100491,"name": " IEEE Transactions on Systems  Man  and Cybernetics " },
{"articles":[[1996,86],[1997,69],[1998,81],[1999,78],[2000,85]],"total": 100890,"name": " IEEE Transactions on Systems  Man  and Cybernetics  Part A " },
{"articles":[[1996,84],[1997,109],[1998,100],[1999,96],[2000,91]],"total": 101370,"name": " IEEE Transactions on Systems  Man  and Cybernetics  Part B " },
{"articles":[[1998,56],[1999,51],[2000,57]],"total": 101534,"name": " IEEE Transactions on Systems  Man  and Cybernetics  Part C " },
{"articles":[[1993,64],[1994,55],[1995,78],[1996,83],[1997,81],[1998,68],[1999,72],[2000,66]],"total": 102101,"name": " IEEE/ACM Trans. Netw. " },
{"articles":[[1995,205]],"total": 102306,"name": " IEICE Transactions " },
{"articles":[[1999,21],[2000,22]],"total": 102349,"name": " IGTR " },
{"articles":[[1991,33],[1992,27],[1993,32],[1994,18],[1995,29],[1996,43],[1997,33],[1998,33],[1999,40],[2000,34]],"total": 102671,"name": " IJAC " },
{"articles":[[1998,15],[1999,20],[2000,20]],"total": 102726,"name": " IJDAR " },
{"articles":[[1990,42],[1991,30],[1992,19],[1993,24],[1994,25],[1995,19],[1996,18],[1997,28],[1998,19],[1999,26],[2000,24]],"total": 103000,"name": " IJHPCA " },
{"articles":[[2000,64]],"total": 103064,"name": " IJMTM " },
{"articles":[[1990,37],[1991,42],[1992,48],[1993,62],[1994,71],[1995,48],[1996,54],[1997,62],[1998,56],[1999,68],[2000,64]],"total": 103676,"name": " IJPRAI " },
{"articles":[[2000,24]],"total": 103700,"name": " IJSTM " },
{"articles":[[2000,89]],"total": 103789,"name": " IJTM " },
{"articles":[[1994,25],[1995,21],[1996,23],[1997,23],[1998,23],[1999,24],[2000,20]],"total": 103948,"name": " IJWIN " },
{"articles":[[1990,40],[1991,44],[1992,74],[1993,66],[1994,66],[1995,62],[1996,63],[1997,75],[1998,79],[1999,95],[2000,88]],"total": 104700,"name": " Image Vision Comput. " },
{"articles":[[1990,12],[1991,14],[1992,11],[1993,17]],"total": 104754,"name": " IMPACT Comput. Sci. Eng. " },
{"articles":[[1998,14],[1999,4],[2000,5]],"total": 104777,"name": " In Silico Biology " },
{"articles":[[2000,30]],"total": 104807,"name": " Industrial Management and Data Systems " },
{"articles":[[1990,53],[1991,66],[1992,59],[1993,65],[1994,94],[1995,163],[1996,87],[1997,50],[1998,61],[1999,64],[2000,68]],"total": 105637,"name": " Inf. Comput. " },
{"articles":[[1993,27],[1994,29],[1995,31],[1996,37],[1997,29],[1998,27],[1999,27],[2000,26]],"total": 105870,"name": " Inf. Manag. Comput. Security " },
{"articles":[[1990,193],[1991,232],[1992,237],[1993,206],[1994,220],[1995,237],[1996,218],[1997,210],[1998,206],[1999,165],[2000,146]],"total": 108140,"name": " Inf. Process. Lett. " },
{"articles":[[1990,54],[1991,47],[1992,56],[1993,55],[1994,60],[1995,55],[1996,68],[1997,77],[1998,66],[1999,55],[2000,46]],"total": 108779,"name": " Inf. Process. Manage. " },
{"articles":[[1995,9],[1996,16],[1997,24],[1998,19],[1999,19],[2000,42]],"total": 108908,"name": " Inf. Res. " },
{"articles":[[1999,10],[2000,42]],"total": 108960,"name": " Inf. Retr. " },
{"articles":[[1990,43],[1991,87],[1992,113],[1993,116],[1994,105],[1995,84],[1996,124],[1997,104],[1998,151],[1999,139],[2000,135]],"total": 110161,"name": " Inf. Sci. " },
{"articles":[[1996,29],[1997,34],[1998,48],[1999,31],[2000,30]],"total": 110333,"name": " Inf. Sec. Techn. Report " },
{"articles":[[1990,8],[1992,18],[1993,19],[1994,19],[1995,29],[1996,59],[1997,33],[1998,32],[1999,32],[2000,30]],"total": 110612,"name": " Inf. Soc. " },
{"articles":[[1990,53],[1991,40],[1992,31],[1993,40],[1994,41],[1995,34],[1996,32],[1997,23],[1998,30],[1999,30],[2000,29]],"total": 110995,"name": " Inf. Syst. " },
{"articles":[[1991,21],[1992,22],[1993,19],[1994,19],[1995,21],[1996,19],[1997,18],[1998,19],[1999,21],[2000,20]],"total": 111194,"name": " Inf. Syst. J. " },
{"articles":[[1990,15],[1991,18],[1992,22],[1993,14],[1994,14],[1995,17],[1996,20],[1997,23],[1998,25],[1999,23],[2000,20]],"total": 111405,"name": " Inform.  Forsch. Entwickl. " },
{"articles":[[1998,30],[1999,28],[2000,37]],"total": 111500,"name": " Informatica  Lith. Acad. Sci. " },
{"articles":[[1993,29],[1994,37],[1995,50],[1996,29],[1997,51],[1998,43],[1999,57],[2000,54]],"total": 111850,"name": " Informatica (Slovenia) " },
{"articles":[[2000,3]],"total": 111853,"name": " Informatica Didactica " },
{"articles":[[1990,36],[1991,39],[1992,37],[1993,36],[1994,49],[1995,41],[1996,35],[1997,41],[1998,41],[1999,43],[2000,41]],"total": 112292,"name": " Informatik Spektrum " },
{"articles":[[1999,18],[2000,12]],"total": 112322,"name": " Information  Knowledge  Systems Management " },
{"articles":[[1990,54],[1991,55],[1992,61],[1993,60],[1994,60],[1995,62],[1996,47],[1997,42],[1998,48],[1999,53],[2000,38]],"total": 112902,"name": " Information & Management " },
{"articles":[[1993,95],[1994,89],[1995,79],[1996,73],[1997,79],[1998,81],[1999,88],[2000,85]],"total": 113571,"name": " Information & Software Technology " },
{"articles":[[2000,23]],"total": 113594,"name": " Information Economics and Policy " },
{"articles":[[2000,12]],"total": 113606,"name": " Information Fusion " },
{"articles":[[1999,25],[2000,34]],"total": 113665,"name": " Information Systems Frontiers " },
{"articles":[[1990,19],[1991,12],[1992,16],[1993,14],[1994,21],[1995,16],[1996,27],[1997,21],[1998,22],[1999,22],[2000,26]],"total": 113881,"name": " Information Systems Research " },
{"articles":[[1992,13],[1993,47],[1994,34],[1995,42],[1996,8],[1997,20],[1998,38],[1999,37],[2000,45]],"total": 114165,"name": " Information Systems Security " },
{"articles":[[2000,24]],"total": 114189,"name": " Information Technology and Management " },
{"articles":[[1998,9],[1999,11],[2000,26]],"total": 114235,"name": " InformingSciJ " },
{"articles":[[1990,35],[1991,41],[1992,42],[1993,44],[1994,45],[1995,42],[1996,41],[1997,41],[1998,42],[1999,35],[2000,26]],"total": 114669,"name": " INFORMS Journal on Computing " },
{"articles":[[2000,47]],"total": 114716,"name": " Int J. Information Management " },
{"articles":[[1990,18],[1991,25],[1992,32],[1993,28],[1994,28],[1995,31],[1996,31],[1997,38],[1998,41],[1999,34],[2000,34]],"total": 115056,"name": " Int. J. Approx. Reasoning " },
{"articles":[[1997,25],[1998,37],[1999,29],[2000,42]],"total": 115189,"name": " Int. J. Communication Systems " },
{"articles":[[1991,30],[1992,25],[1993,28],[1994,24],[1995,25],[1996,30],[1997,36],[1998,30],[1999,34],[2000,35]],"total": 115486,"name": " Int. J. Comput. Geometry Appl. " },
{"articles":[[1999,40],[2000,96]],"total": 115622,"name": " Int. J. Comput. Math. " },
{"articles":[[2000,22]],"total": 115644,"name": " Int. J. Comput. Proc. Oriental Lang. " },
{"articles":[[2000,21]],"total": 115665,"name": " Int. J. Comput. Syst. Signal " },
{"articles":[[1998,43],[1999,41],[2000,46]],"total": 115795,"name": " Int. J. Computer Integrated Manufacturing " },
{"articles":[[1992,22],[1993,21],[1994,21],[1995,19],[1996,18],[1997,16],[1998,16],[1999,13],[2000,20]],"total": 115961,"name": " Int. J. Cooperative Inf. Syst. " },
{"articles":[[1990,30],[1991,19],[1992,23],[1993,22],[1994,18],[1995,22],[1996,25],[1997,26],[1998,24],[1999,34],[2000,33]],"total": 116237,"name": " Int. J. Found. Comput. Sci. " },
{"articles":[[1997,36],[1998,40],[1999,36],[2000,31]],"total": 116380,"name": " Int. J. Game Theory " },
{"articles":[[1990,21],[1991,26],[1992,22],[1993,22],[1994,22],[1995,24],[1996,26],[1997,28],[1998,18],[1999,18],[2000,26]],"total": 116633,"name": " Int. J. Hum. Comput. Interaction " },
{"articles":[[1994,77],[1995,73],[1996,67],[1997,67],[1998,74],[1999,80],[2000,90]],"total": 117161,"name": " Int. J. Hum.-Comput. Stud. " },
{"articles":[[1990,37],[1991,35],[1992,38],[1994,40],[1995,45],[1996,50],[1997,62],[1998,54],[1999,49],[2000,40]],"total": 117611,"name": " Int. J. Imaging Systems and Technology " },
{"articles":[[1990,22],[1991,29],[1992,46],[1993,37],[1994,54],[1995,47],[1996,50],[1997,49],[1998,63],[1999,64],[2000,62]],"total": 118134,"name": " Int. J. Intell. Syst. " },
{"articles":[[1990,9],[1991,40],[1992,68],[1993,37],[1994,36],[1995,36],[1996,74],[1997,57],[1999,56],[2000,39]],"total": 118586,"name": " Int. J. Neural Syst. " },
{"articles":[[1997,31],[1998,5],[1999,12],[2000,26]],"total": 118660,"name": " Int. J. on Digital Libraries " },
{"articles":[[1997,25],[1998,25],[1999,33],[2000,26]],"total": 118769,"name": " Int. J. Satellite Communications Networking " },
{"articles":[[1997,130],[1998,133],[1999,122],[2000,141]],"total": 119295,"name": " Int. J. Systems Science " },
{"articles":[[1991,22],[1992,6],[1994,22],[1996,22]],"total": 119367,"name": " Int. Journal in Computer Simulation " },
{"articles":[[1991,16],[1992,25],[1993,18],[1994,31],[1995,33],[1996,39],[1997,34],[1998,39],[1999,45],[2000,33]],"total": 119680,"name": " Int. Journal of Network Management " },
{"articles":[[1996,17],[1997,21],[1998,18],[1999,21],[2000,17]],"total": 119774,"name": " Int. Syst. in Accounting  Finance and Management " },
{"articles":[[1998,24],[1999,25],[2000,24]],"total": 119847,"name": " Integrated Computer-Aided Engineering " },
{"articles":[[1990,28],[1991,49],[1992,26],[1993,39],[1994,18],[1995,19],[1996,17],[1997,30],[1998,22],[1999,16],[2000,20]],"total": 120131,"name": " Integration " },
{"articles":[[1997,24],[1998,23],[1999,14],[2000,29]],"total": 120221,"name": " Inteligencia Artificial  Revista Iberoamericana de Inteligencia Artificial " },
{"articles":[[1997,21],[1998,24],[1999,31],[2000,36]],"total": 120333,"name": " Intell. Data Anal. " },
{"articles":[[1999,34],[2000,35]],"total": 120402,"name": " Intelligence " },
{"articles":[[1995,35],[1996,33],[1997,30],[1998,28],[1999,27],[2000,29]],"total": 120584,"name": " Intelligent Automation & Soft Computing " },
{"articles":[[1990,13],[1991,15],[1992,14],[1993,13],[1994,21],[1995,9],[1996,12],[1997,4]],"total": 120685,"name": " Intelligent Tutoring Media " },
{"articles":[[1990,25],[1991,19],[1992,21],[1993,25],[1994,21],[1995,21],[1996,26],[1997,10],[1998,48],[1999,36],[2000,39]],"total": 120976,"name": " Interacting with Computers " },
{"articles":[[1994,32],[1995,36],[1996,54],[1997,42],[1998,55],[1999,70],[2000,74]],"total": 121339,"name": " Interactions " },
{"articles":[[1990,13],[1992,12],[1993,10],[1994,15],[1998,26],[1999,16],[2000,16]],"total": 121447,"name": " Interactive Learning Environments " },
{"articles":[[2000,16]],"total": 121463,"name": " International Journal of Computational Engineering Science " },
{"articles":[[1990,25],[1991,17],[1992,32],[1993,29],[1994,25],[1995,36],[1996,49],[1997,62],[1998,58],[1999,60],[2000,71]],"total": 121927,"name": " International Journal of Computer Vision " },
{"articles":[[1990,33],[1991,40],[1992,42],[1996,52],[1997,43],[1998,44],[1999,46],[2000,46]],"total": 122273,"name": " International Journal of Geographical Information Science " },
{"articles":[[1990,1],[1991,1],[1993,35],[1994,31],[1995,36]],"total": 122377,"name": " International Journal of Geographical Information Systems " },
{"articles":[[1990,21],[1991,14],[1992,19],[1993,25],[1994,26],[1995,31],[1996,20],[1997,20],[1999,20],[2000,14]],"total": 122587,"name": " International Journal of High Speed Computing " },
{"articles":[[1990,72],[1991,94],[1992,90],[1993,107]],"total": 122950,"name": " International Journal of Man-Machine Studies " },
{"articles":[[1990,20],[1991,20],[1992,18],[1994,24],[1995,22],[1996,23],[1997,20],[1998,27],[1999,22],[2000,22]],"total": 123168,"name": " International Journal of Parallel Programming " },
{"articles":[[1994,12],[1996,14],[1997,11],[1998,13],[1999,15],[2000,13]],"total": 123246,"name": " International Journal of Shape Modeling " },
{"articles":[[1991,29],[1992,31],[1993,28],[1994,27],[1995,31],[1996,30],[1997,29],[1998,28],[1999,35],[2000,36]],"total": 123550,"name": " International Journal of Software Engineering and Knowledge Engineering " },
{"articles":[[1993,9],[1994,35],[1995,24],[1996,39],[1997,47],[1998,43],[1999,46],[2000,44]],"total": 123837,"name": " International Journal of Uncertainty  Fuzziness and Knowledge-Based Systems " },
{"articles":[[1992,21],[1993,25],[1994,29],[1995,26],[1996,26],[1997,30],[1998,22],[1999,28],[2000,34]],"total": 124078,"name": " International Journal on Artificial Intelligence Tools " },
{"articles":[[1995,23],[1996,36],[1997,37],[1998,43],[1999,34],[2000,37]],"total": 124288,"name": " Internet Research " },
{"articles":[[2000,15]],"total": 124303,"name": " IRMJ " },
{"articles":[[1996,58],[1997,60],[1998,58],[1999,52],[2000,50]],"total": 124581,"name": " IS Management " },
{"articles":[[1995,15],[1996,15],[1997,16],[1998,19],[1999,17],[2000,18]],"total": 124681,"name": " IT & People " },
{"articles":[[1990,55],[1991,44],[1992,42]],"total": 124822,"name": " it - Informationstechnik " },
{"articles":[[1993,33],[1994,49],[1995,45],[1996,51],[1997,49],[1998,48],[1999,49],[2000,45]],"total": 125191,"name": " it+ti - Informationstechnik und Technische Informatik " },
{"articles":[[1990,31],[1991,29],[1992,28],[1993,32],[1994,26],[1995,28],[1996,28],[1997,26],[1998,4],[1999,32],[2000,33]],"total": 125488,"name": " ITA " },
{"articles":[[1990,38],[1991,53],[1992,32],[1999,1]],"total": 125612,"name": " IWBS Report " },
{"articles":[[1990,36],[1991,37],[1992,38],[1993,45],[1994,47],[1995,44],[1996,32],[1997,34],[1998,31],[1999,27],[2000,35]],"total": 126018,"name": " J. ACM " },
{"articles":[[2000,12]],"total": 126030,"name": " J. AIS " },
{"articles":[[1990,30],[1991,38],[1992,38],[1993,49],[1994,42],[1995,46],[1996,57],[1997,76],[1998,65],[1999,60],[2000,67]],"total": 126598,"name": " J. Algorithms " },
{"articles":[[1993,6],[1994,14],[1995,27],[1996,28],[1997,19],[1998,20],[1999,28],[2000,20]],"total": 126760,"name": " J. Artif. Intell. Res. (JAIR) " },
{"articles":[[1998,32],[1999,31],[2000,25]],"total": 126848,"name": " J. Artificial Societies and Social Simulation " },
{"articles":[[1990,25],[1991,31],[1992,38],[1993,39],[1994,34],[1995,27],[1996,25],[1997,41],[1998,29],[1999,30],[2000,26]],"total": 127193,"name": " J. Autom. Reasoning " },
{"articles":[[1997,16],[1998,19],[1999,13],[2000,8]],"total": 127249,"name": " J. Braz. Comp. Soc. " },
{"articles":[[2000,21]],"total": 127270,"name": " J. Classification " },
{"articles":[[1997,16],[1998,28],[1999,28],[2000,25]],"total": 127367,"name": " J. Comb. Optim. " },
{"articles":[[1990,69],[1991,76],[1992,85],[1993,69],[1994,96],[1995,91],[1996,105],[1997,97],[1998,66],[1999,96],[2000,88]],"total": 128305,"name": " J. Comb. Theory  Ser. A " },
{"articles":[[1990,67],[1991,63],[1992,64],[1993,69],[1994,73],[1995,55],[1996,67],[1997,62],[1998,66],[1999,56],[2000,55]],"total": 129002,"name": " J. Comb. Theory  Ser. B " },
{"articles":[[1997,30],[1998,36],[1999,41],[2000,42]],"total": 129151,"name": " J. Comp. Assisted Learning " },
{"articles":[[1990,25],[1991,29],[1992,27],[1993,32],[1994,25],[1995,25],[1996,35],[1997,31],[1998,27],[1999,32],[2000,34]],"total": 129473,"name": " J. Complexity " },
{"articles":[[1993,44],[1994,37],[1995,58],[1996,62],[1997,58],[1998,71],[1999,73],[2000,73]],"total": 129949,"name": " J. Comput. Sci. Technol. " },
{"articles":[[1990,33],[1991,37],[1992,44],[1993,35],[1994,60],[1995,83],[1996,81],[1997,68],[1998,49],[1999,62],[2000,52]],"total": 130553,"name": " J. Comput. Syst. Sci. " },
{"articles":[[1995,19],[1996,24],[1997,28],[1998,17],[1999,24],[2000,18]],"total": 130683,"name": " J. Computer-Mediated Communication " },
{"articles":[[1990,10],[1991,13],[1992,12],[1993,17],[1994,16],[1995,15],[1996,16],[1997,18],[1998,18],[1999,13],[2000,17]],"total": 130848,"name": " J. Computing in Higher Education " },
{"articles":[[1990,14],[1991,19],[1992,13],[1993,14],[1994,12],[1995,13],[1996,15],[1997,16],[1998,17],[1999,16],[2000,20]],"total": 131017,"name": " J. Cryptology " },
{"articles":[[1998,25],[1999,20],[2000,12]],"total": 131074,"name": " J. Database Manag. " },
{"articles":[[1997,9],[1998,3],[1999,6],[2000,6]],"total": 131098,"name": " J. Digit. Inf. " },
{"articles":[[1992,40],[1993,28],[1994,36],[1995,28],[1996,28],[1997,30],[1998,25],[1999,30],[2000,32]],"total": 131375,"name": " J. Digital Imaging " },
{"articles":[[2000,73]],"total": 131448,"name": " J. Economic Theory " },
{"articles":[[2000,13]],"total": 131461,"name": " J. Electron. Commerce Res. " },
{"articles":[[1992,44],[1993,41],[1994,43],[1995,39],[1996,48],[1997,52],[1998,83],[1999,46],[2000,55]],"total": 131912,"name": " J. Electronic Imaging " },
{"articles":[[1990,20],[1991,33],[1992,36],[1993,35],[1994,36],[1995,50],[1996,45],[1997,51],[1998,50],[1999,55],[2000,59]],"total": 132382,"name": " J. Electronic Testing " },
{"articles":[[1990,20],[1991,22],[1992,21],[1993,23],[1994,20],[1995,24],[1996,24],[1997,31],[1998,32],[1999,30],[2000,33]],"total": 132662,"name": " J. Exp. Theor. Artif. Intell. " },
{"articles":[[1990,42],[1991,39],[1992,53],[1993,51],[1994,57],[1995,64],[1996,59],[1997,63],[1998,48],[1999,48],[2000,48]],"total": 133234,"name": " J. Field Robotics " },
{"articles":[[1991,18],[1992,21],[1993,25],[1994,20],[1995,23],[1996,35],[1997,25],[1998,25],[1999,27],[2000,23]],"total": 133476,"name": " J. Funct. Program. " },
{"articles":[[1999,24],[2000,78]],"total": 133578,"name": " J. Global Optimization " },
{"articles":[[1997,3],[1998,8],[1999,8],[2000,12]],"total": 133609,"name": " J. Graph Algorithms Appl. " },
{"articles":[[1996,16],[1997,16],[1998,13],[1999,19],[2000,16]],"total": 133689,"name": " J. Graphics  GPU  & Game Tools " },
{"articles":[[1995,9],[1996,12],[1997,21],[1998,23],[1999,22],[2000,26]],"total": 133802,"name": " J. Heuristics " },
{"articles":[[1992,18],[1993,19],[1994,24],[1995,28],[1996,27],[1997,20],[1998,17],[1999,18],[2000,15]],"total": 133988,"name": " J. High Speed Networks " },
{"articles":[[1990,24],[1991,24],[1992,32],[1993,30],[1994,32],[1995,32],[1996,35],[1997,34],[1998,42],[1999,52],[2000,48]],"total": 134373,"name": " J. Inf. Sci. Eng. " },
{"articles":[[1999,6],[2000,14]],"total": 134393,"name": " J. Instruction-Level Parallelism " },
{"articles":[[1992,13],[1993,16],[1994,13],[1995,26],[1996,25],[1997,25],[1998,21],[1999,22],[2000,26]],"total": 134580,"name": " J. Intell. Inf. Syst. " },
{"articles":[[1993,14],[1994,17],[1995,20],[1996,14],[1997,5],[1998,5],[1999,18],[2000,12]],"total": 134685,"name": " J. Intellig. Transport. Systems " },
{"articles":[[1990,20],[1991,37],[1992,34],[1993,33],[1994,35],[1995,37],[1996,48],[1997,50],[1998,59],[1999,49],[2000,43]],"total": 135130,"name": " J. Intelligent Manufacturing " },
{"articles":[[1997,33],[1998,18],[1999,26],[2000,32]],"total": 135239,"name": " J. Knowledge Management " },
{"articles":[[1990,11],[1991,23],[1992,31],[1993,34],[1994,40],[1995,30],[1996,34],[1997,32],[1998,38],[1999,40],[2000,34]],"total": 135586,"name": " J. Log. Comput. " },
{"articles":[[1990,28],[1991,28],[1992,44],[1993,39],[1994,32],[1995,32],[1996,41],[1997,39],[1998,33],[1999,41],[2000,36]],"total": 135979,"name": " J. Log. Program. " },
{"articles":[[1998,18],[1999,18],[2000,28]],"total": 136043,"name": " J. Network and Computer Applications " },
{"articles":[[1993,25],[1994,24],[1995,28],[1996,26],[1997,29],[1998,35],[1999,32],[2000,31]],"total": 136273,"name": " J. Network Syst. Manage. " },
{"articles":[[2000,25]],"total": 136298,"name": " J. Nonlinear Science " },
{"articles":[[1998,5],[1999,13],[2000,14]],"total": 136330,"name": " J. of IT & Tourism " },
{"articles":[[1990,32],[1991,32],[1992,37],[1993,42],[1994,39],[1995,39],[1996,42],[1997,41],[1998,42],[1999,36],[2000,41]],"total": 136753,"name": " J. of Management Information Systems " },
{"articles":[[2000,18]],"total": 136771,"name": " J. Org. Computing and E. Commerce " },
{"articles":[[1990,123],[1991,113],[1992,102],[1993,117],[1994,155],[1995,150],[1996,156],[1997,138],[1998,81],[1999,74],[2000,69]],"total": 138049,"name": " J. Parallel Distrib. Comput. " },
{"articles":[[1990,17],[1991,17],[1992,17],[1993,28],[1994,24],[1995,28],[1996,26],[1997,35],[1998,23],[1999,28],[2000,24]],"total": 138316,"name": " J. Philosophical Logic " },
{"articles":[[1995,8],[1996,11],[1997,9],[1998,3]],"total": 138347,"name": " J. Prog. Lang. " },
{"articles":[[1998,22],[1999,18],[2000,20]],"total": 138407,"name": " J. Sci. Comput. " },
{"articles":[[1991,8],[1992,37],[1993,27],[1994,36],[1995,30],[1996,26],[1997,19],[1998,19],[1999,33],[2000,18]],"total": 138660,"name": " J. Strategic Inf. Sys. " },
{"articles":[[1990,80],[1991,64],[1992,68],[1993,78],[1994,63],[1995,74],[1996,71],[1997,77],[1998,74],[1999,67],[2000,92]],"total": 139468,"name": " J. Symb. Comput. " },
{"articles":[[1990,81],[1991,100],[1992,86],[1993,79],[1994,92],[1995,74],[1996,69],[1997,81],[1998,90],[1999,111],[2000,110]],"total": 140441,"name": " J. Symb. Log. " },
{"articles":[[1994,6],[1995,69],[1996,54],[1997,78],[1998,70],[1999,60],[2000,81]],"total": 140859,"name": " J. UCS " },
{"articles":[[1990,22],[1991,25],[1992,20],[1993,21],[1994,20],[1995,23],[1996,23],[1997,26],[1998,28],[1999,33],[2000,33]],"total": 141133,"name": " J. Vis. Lang. Comput. " },
{"articles":[[1997,32],[1998,33],[1999,21],[2000,26]],"total": 141245,"name": " J. Visual Communication and Image Representation " },
{"articles":[[1997,20],[1998,34],[1999,75],[2000,65]],"total": 141439,"name": " JACIII " },
{"articles":[[1997,7],[1998,12],[1999,12],[2000,15]],"total": 141485,"name": " JAMDS " },
{"articles":[[1994,51],[1995,51],[1996,46],[1997,58],[1998,66],[1999,53],[2000,71]],"total": 141881,"name": " JAMIA " },
{"articles":[[1990,95],[1991,103],[1992,71],[1993,55],[1994,77],[1995,107],[1996,143],[1997,125],[1998,154],[1999,156],[2000,144]],"total": 143111,"name": " JASIS " },
{"articles":[[2000,16]],"total": 143127,"name": " JGIM " },
{"articles":[[2000,15]],"total": 143142,"name": " JOEUC " },
{"articles":[[1994,64],[1995,87],[1996,102],[1997,100],[1998,99],[1999,23]],"total": 143617,"name": " JOOP " },
{"articles":[[1992,9],[1993,9],[1994,11],[1995,11],[1996,17],[1997,14],[1998,15],[1999,25],[2000,16]],"total": 143744,"name": " Journal of Applied Non-Classical Logics " },
{"articles":[[1996,18],[1997,14],[1998,7],[1999,20],[2000,29]],"total": 143832,"name": " Journal of Automata  Languages and Combinatorics " },
{"articles":[[1990,80],[1991,92],[1992,123],[1993,137],[1994,194],[1995,145],[1996,192],[1997,214],[1998,173],[1999,169],[2000,191]],"total": 145542,"name": " Journal of Chemical Information and Computer Sciences " },
{"articles":[[1991,21],[1992,24],[1993,48],[1994,28],[1995,46],[1996,46],[1997,45],[1998,37],[1999,25],[2000,20]],"total": 145882,"name": " Journal of Circuits  Systems  and Computers " },
{"articles":[[1999,32],[2000,45]],"total": 145959,"name": " Journal of Communications and Networks " },
{"articles":[[1994,30],[1995,39],[1996,31],[1997,38],[1998,50],[1999,31],[2000,52]],"total": 146230,"name": " Journal of Computational Biology " },
{"articles":[[1993,163],[1994,123],[1995,125],[1996,144],[1997,138],[1998,159],[1999,152],[2000,128]],"total": 147362,"name": " Journal of Computational Chemistry " },
{"articles":[[1994,20],[1995,20],[1996,18],[1997,19],[1998,23],[1999,29],[2000,28]],"total": 147519,"name": " Journal of Computational Neuroscience " },
{"articles":[[1992,14],[1993,17],[1995,14],[1996,13],[1997,16],[1998,10],[1999,10],[2000,12]],"total": 147625,"name": " Journal of Computer Security " },
{"articles":[[1992,41],[1993,40],[1994,51],[1995,45],[1996,52],[1997,51],[1998,47],[1999,44],[2000,55]],"total": 148051,"name": " Journal of Computer-Aided Molecular Design " },
{"articles":[[2000,8]],"total": 148059,"name": " Journal of Decision Systems " },
{"articles":[[1995,2],[1996,4],[1997,7],[1998,7],[1999,17],[2000,7]],"total": 148103,"name": " Journal of Functional and Logic Programming " },
{"articles":[[1999,20],[2000,32]],"total": 148155,"name": " Journal of Geographical Systems " },
{"articles":[[1990,71],[1991,49],[1992,54],[1993,68],[1994,56],[1995,92],[1996,132],[1997,81],[1998,61],[1999,94],[2000,73]],"total": 148986,"name": " Journal of Graph Theory " },
{"articles":[[1996,91],[1997,116],[1998,70],[1999,52],[2000,56]],"total": 149371,"name": " Journal of Information  Law and Technology " },
{"articles":[[1993,31],[1994,30],[1995,30],[1996,26],[1997,30],[1998,37],[1999,29],[2000,37]],"total": 149621,"name": " Journal of Intelligent and Fuzzy Systems " },
{"articles":[[1990,28],[1991,21],[1992,38],[1993,37],[1994,49],[1995,48],[1996,60],[1997,61],[1998,61],[1999,63],[2000,61]],"total": 150148,"name": " Journal of Intelligent and Robotic Systems " },
{"articles":[[2000,18]],"total": 150166,"name": " Journal of Interconnection Networks " },
{"articles":[[1992,10],[1993,10],[1994,11],[1995,18],[1996,13],[1997,20],[1998,32],[1999,35],[2000,30]],"total": 150345,"name": " Journal of Logic  Language and Information " },
{"articles":[[2000,4]],"total": 150349,"name": " Journal of Machine Learning Research " },
{"articles":[[1992,35],[1993,16],[1994,24],[1995,22],[1996,23],[1997,25],[1998,26],[1999,34],[2000,26]],"total": 150580,"name": " Journal of Mathematical Imaging and Vision " },
{"articles":[[1994,23],[1995,23],[1996,22],[1997,31],[1998,28],[1999,23],[2000,21]],"total": 150751,"name": " Journal of Quantitative Linguistics " },
{"articles":[[2000,14]],"total": 150765,"name": " Journal of Research and Practice in Information Technology " },
{"articles":[[2000,4]],"total": 150769,"name": " Journal of Social Structure " },
{"articles":[[1990,15],[1991,16],[1992,15],[1993,15],[1994,23],[1995,32],[1996,21],[1997,20],[1998,19],[1999,20],[2000,19]],"total": 150984,"name": " Journal of Software Maintenance " },
{"articles":[[1990,78],[1991,80],[1992,81],[1993,99],[1994,93],[1995,92],[1996,90],[1997,89],[1998,109],[1999,110],[2000,131]],"total": 152036,"name": " Journal of Systems and Software " },
{"articles":[[1996,51],[1997,90],[1998,74],[1999,60],[2000,95]],"total": 152406,"name": " Journal of Systems Architecture " },
{"articles":[[1991,19],[1992,18],[1993,16],[1994,15],[1995,16],[1996,13],[1997,16],[1998,17],[1999,14],[2000,6]],"total": 152556,"name": " Journal of Systems Integration " },
{"articles":[[1990,15],[1991,27],[1992,19],[1993,20],[1994,15],[1995,19],[1996,20],[1997,17],[1998,20],[1999,21],[2000,26]],"total": 152775,"name": " Journal of Visualization and Computer Animation " },
{"articles":[[1990,66],[1991,65],[1992,69],[1993,61],[1994,60],[1995,58],[1996,40],[1997,47],[1998,42],[1999,68],[2000,72]],"total": 153423,"name": " KI " },
{"articles":[[1999,23],[2000,26]],"total": 153472,"name": " Knowl. Inf. Syst. " },
{"articles":[[1990,40],[1991,30],[1992,33],[1993,32],[1994,42],[1995,36],[1996,48],[1997,23],[1998,70],[1999,45],[2000,52]],"total": 153923,"name": " Knowl.-Based Syst. " },
{"articles":[[1990,29],[1991,45],[1992,29],[1993,23],[1994,59],[1995,50],[1996,39],[1997,34],[1998,31],[1999,39],[2000,11]],"total": 154312,"name": " Knowledge Eng. Review " },
{"articles":[[1990,5],[1991,4],[1993,1],[1997,18],[1998,27],[1999,14],[2000,14]],"total": 154395,"name": " Kognitionswissenschaft " },
{"articles":[[1998,15],[1999,20],[2000,21]],"total": 154451,"name": " L'OBJET " },
{"articles":[[1990,6],[1991,8],[1992,12],[1993,11],[1994,14],[1995,12],[1996,5],[1997,18],[1998,20],[1999,11],[2000,8]],"total": 154576,"name": " LDV Forum " },
{"articles":[[1997,43],[1998,32],[1999,38],[2000,35]],"total": 154724,"name": " Learned Publishing " },
{"articles":[[1992,43],[1993,29],[1994,38],[1995,52],[1996,38],[1997,48],[1998,38],[1999,46],[2000,35]],"total": 155091,"name": " Library Trends " },
{"articles":[[1990,15],[1991,11],[1992,16],[1993,12],[1994,14],[1995,12],[1996,10],[1997,6],[1998,4]],"total": 155191,"name": " Lisp and Symbolic Computation " },
{"articles":[[1996,75],[1997,72],[1998,49],[1999,44],[2000,49]],"total": 155480,"name": " LOG IN " },
{"articles":[[1993,7],[1994,6],[1995,46],[1996,24],[1997,40],[1998,46],[1999,37],[2000,36]],"total": 155722,"name": " Logic Journal of the IGPL " },
{"articles":[[1992,25],[1993,17]],"total": 155764,"name": " LOPLAS " },
{"articles":[[1990,19],[1991,23],[1992,23],[1993,23],[1994,23],[1995,45],[1996,14],[1997,38],[1998,21],[1999,10],[2000,36]],"total": 156039,"name": " Mach. Vis. Appl. " },
{"articles":[[1990,18],[1991,28],[1992,31],[1993,46],[1994,53],[1995,45],[1996,44],[1997,44],[1998,49],[1999,45],[2000,45]],"total": 156487,"name": " Machine Learning " },
{"articles":[[1990,26],[1991,21],[1992,28],[1993,19],[1994,12],[1995,12],[1996,7],[1997,18],[1998,13],[1999,11],[2000,15]],"total": 156669,"name": " Machine Translation " },
{"articles":[[1999,21],[2000,29]],"total": 156719,"name": " Markup Languages " },
{"articles":[[1996,111],[1997,105],[1998,100],[1999,103],[2000,94]],"total": 157232,"name": " Math. Comput. " },
{"articles":[[1990,56],[1991,59],[1992,53],[1993,57],[1994,50],[1995,44],[1996,44],[1997,47],[1998,46],[1999,44],[2000,49]],"total": 157781,"name": " Math. Log. Q. " },
{"articles":[[1994,39],[1995,48],[1996,53],[1997,55],[1998,55],[1999,59],[2000,55]],"total": 158145,"name": " Math. Meth. of OR " },
{"articles":[[2000,41]],"total": 158186,"name": " Math. Oper. Res. " },
{"articles":[[1990,73],[1991,103],[1992,102],[1993,117],[1994,95],[1995,75],[1996,96],[1997,60],[1998,78],[1999,100],[2000,68]],"total": 159153,"name": " Math. Program. " },
{"articles":[[2000,40]],"total": 159193,"name": " Mathematical Social Sciences " },
{"articles":[[1991,12],[1992,19],[1993,16],[1994,17],[1995,22],[1996,27],[1997,25],[1998,21],[1999,28],[2000,26]],"total": 159406,"name": " Mathematical Structures in Computer Science " },
{"articles":[[1990,16],[1991,17],[1992,17],[1993,18],[1994,26],[1995,29],[1996,36]],"total": 159565,"name": " Mathematical Systems Theory " },
{"articles":[[1991,22],[1992,24],[1993,22],[1994,17],[1995,19],[1996,19],[1997,18],[1998,17],[1999,15],[2000,17]],"total": 159755,"name": " MCSS " },
{"articles":[[1996,11],[1997,13],[1998,24],[1999,28],[2000,28]],"total": 159859,"name": " Medical Image Analysis " },
{"articles":[[1994,21]],"total": 159880,"name": " Meth. of Logic in CS " },
{"articles":[[1992,106],[1993,240],[1994,104],[1995,33],[1996,17]],"total": 160380,"name": " Microprocessing and Microprogramming " },
{"articles":[[1992,54],[1993,86],[1994,78],[1995,69],[1996,36],[1997,61],[1998,66],[1999,86],[2000,43]],"total": 160959,"name": " Microprocessors and Microsystems - Embedded Hardware Design " },
{"articles":[[1991,24],[1992,23],[1993,26],[1994,27],[1995,31],[1996,21],[1997,37],[1998,36],[1999,50],[2000,49]],"total": 161283,"name": " Minds and Machines " },
{"articles":[[1990,24],[1991,27],[1992,26],[1993,21],[1994,22],[1995,26],[1996,25],[1997,25],[1998,26],[1999,26],[2000,28]],"total": 161559,"name": " MIS Quarterly " },
{"articles":[[1999,8],[2000,5]],"total": 161572,"name": " MMI Interaktiv " },
{"articles":[[1997,18],[1998,31],[1999,31],[2000,39]],"total": 161691,"name": " Mobile Computing and Communications Review " },
{"articles":[[1996,39],[1997,34],[1998,32],[1999,28],[2000,31]],"total": 161855,"name": " MONET " },
{"articles":[[1995,17],[1996,18],[1997,17],[1998,19],[1999,16],[2000,19]],"total": 161961,"name": " Monte Carlo Meth. and Appl. " },
{"articles":[[1993,12],[1994,32],[1995,30],[1996,31],[1997,32],[1998,32],[1999,46],[2000,20]],"total": 162196,"name": " Multimedia Syst. " },
{"articles":[[1995,15],[1996,23],[1997,32],[1998,26],[1999,35],[2000,37]],"total": 162364,"name": " Multimedia Tools Appl. " },
{"articles":[[1995,22],[1996,35],[1997,18],[1998,36],[1999,24],[2000,23]],"total": 162522,"name": " Natural Language Engineering " },
{"articles":[[1998,27],[1999,21]],"total": 162570,"name": " Networking and Information Systems " },
{"articles":[[1990,49],[1991,44],[1992,42],[1993,68],[1994,52],[1995,45],[1996,47],[1997,53],[1998,51],[1999,60],[2000,53]],"total": 163134,"name": " Networks " },
{"articles":[[1990,49],[1991,52],[1992,65],[1993,73],[1994,78],[1995,31],[1996,21],[1997,91],[1998,105],[1999,95],[2000,116]],"total": 163910,"name": " Neural Computation " },
{"articles":[[1993,29],[1994,21],[1995,23],[1996,25],[1997,42],[1998,38],[1999,40],[2000,36]],"total": 164164,"name": " Neural Computing and Applications " },
{"articles":[[1990,57],[1991,69],[1992,81],[1993,103],[1994,117],[1995,112],[1996,118],[1997,130],[1998,128],[1999,109],[2000,88]],"total": 165276,"name": " Neural Networks " },
{"articles":[[1993,34],[1994,35],[1995,38],[1996,34],[1997,15],[1998,28],[1999,34],[2000,26]],"total": 165520,"name": " Neural Parallel & Scientific Comp. " },
{"articles":[[1994,16],[1995,42],[1996,35],[1997,35],[1998,44],[1999,53],[2000,44]],"total": 165789,"name": " Neural Processing Letters " },
{"articles":[[1990,20],[1991,18],[1992,22],[1993,16],[1994,29],[1995,54],[1996,83],[1997,65],[1998,101],[1999,180],[2000,220]],"total": 166597,"name": " Neurocomputing " },
{"articles":[[1996,16]],"total": 166613,"name": " NeuroImage " },
{"articles":[[1990,29],[1991,37],[1992,14],[1993,21],[1994,21],[1995,13],[1996,17],[1997,17],[1998,14],[1999,22],[2000,33]],"total": 166851,"name": " New Generation Comput. " },
{"articles":[[1999,34],[2000,34]],"total": 166919,"name": " New Media & Society " },
{"articles":[[1994,28],[1995,23],[1996,25],[1997,20],[1998,18],[1999,29],[2000,24]],"total": 167086,"name": " Nord. J. Comput. " },
{"articles":[[1990,45],[1991,41],[1992,51],[1993,41],[1994,39],[1995,40],[1996,34],[1997,34],[1998,41],[1999,41],[2000,21]],"total": 167514,"name": " Notre Dame Journal of Formal Logic " },
{"articles":[[1990,138],[1991,103],[1992,78],[1993,52],[1994,61],[1995,61],[1996,84],[1997,82],[1998,129],[1999,136],[2000,137]],"total": 168575,"name": " Nucleic Acids Research " },
{"articles":[[1993,73],[1994,60],[1995,48],[1996,65],[1997,65],[1998,54],[1999,69],[2000,66]],"total": 169075,"name": " Numerical Algorithms " },
{"articles":[[1994,32],[1995,33],[1996,30],[1997,27],[1998,24],[1999,38],[2000,38]],"total": 169297,"name": " Numerical Lin. Alg. with Applic. " },
{"articles":[[1996,11],[1997,3],[1998,1]],"total": 169312,"name": " Object Oriented Systems " },
{"articles":[[1999,12],[2000,15]],"total": 169339,"name": " OCLC Systems & Services " },
{"articles":[[1998,52],[1999,14],[2000,39]],"total": 169444,"name": " Online Information Review " },
{"articles":[[1990,2],[1991,36],[1992,29],[1993,133],[1994,73],[1995,51],[1996,14]],"total": 169782,"name": " OOPS Messenger " },
{"articles":[[1993,42],[1994,69],[1995,56],[1996,47],[1997,68],[1998,46],[1999,61],[2000,62]],"total": 170233,"name": " Oper. Res. Lett. " },
{"articles":[[1990,25],[1991,44],[1992,54],[1993,44],[1994,38],[1995,45],[1996,31],[1997,35],[1998,28],[1999,27],[2000,28]],"total": 170632,"name": " Operating Systems Review " },
{"articles":[[1998,93],[1999,83],[2000,83]],"total": 170891,"name": " Operations Research " },
{"articles":[[1999,25],[2000,28]],"total": 170944,"name": " Order " },
{"articles":[[1993,23],[1994,68],[1995,66],[1996,55],[1997,49],[1998,9],[1999,17],[2000,22]],"total": 171253,"name": " Parallel Algorithms Appl. " },
{"articles":[[1990,120],[1991,108],[1992,110],[1993,94],[1994,106],[1995,108],[1996,67],[1997,163],[1998,98],[1999,103],[2000,98]],"total": 172428,"name": " Parallel Computing " },
{"articles":[[1991,19],[1992,43],[1993,53],[1994,43],[1995,59],[1996,51],[1997,37],[1998,52],[1999,50],[2000,32]],"total": 172867,"name": " Parallel Processing Letters " },
{"articles":[[1998,27],[1999,29],[2000,28]],"total": 172951,"name": " Pattern Anal. Appl. " },
{"articles":[[1990,121],[1991,110],[1992,131],[1993,164],[1994,145],[1995,162],[1996,161],[1997,164],[1998,171],[1999,155],[2000,162]],"total": 174597,"name": " Pattern Recognition " },
{"articles":[[1990,105],[1991,102],[1992,102],[1993,124],[1994,151],[1995,146],[1996,167],[1997,169],[1998,140],[1999,157],[2000,113]],"total": 176073,"name": " Pattern Recognition Letters " },
{"articles":[[1990,22],[1991,35],[1992,43],[1993,32],[1994,48],[1995,41],[1996,76],[1997,35],[1998,46],[1999,47],[2000,55]],"total": 176553,"name": " Perform. Eval. " },
{"articles":[[2000,37]],"total": 176590,"name": " Periodica Mathematica Hungarica " },
{"articles":[[1997,28],[1998,25],[1999,24],[2000,31]],"total": 176698,"name": " Personal and Ubiquitous Computing " },
{"articles":[[1999,23],[2000,28]],"total": 176749,"name": " Photonic Network Communications " },
{"articles":[[1999,13],[2000,18]],"total": 176780,"name": " Prague Bull. Math. Linguistics " },
{"articles":[[1990,36],[1991,36],[1992,44],[1993,43],[1994,39],[1995,43],[1996,39],[1997,42],[1998,43],[1999,37],[2000,40]],"total": 177222,"name": " Praxis der Informationsverarbeitung und Kommunikation " },
{"articles":[[1992,41],[1993,29],[1994,29],[1995,27],[1996,33],[1997,48],[1998,42],[1999,48],[2000,44]],"total": 177563,"name": " Presence " },
{"articles":[[1990,45],[1991,45],[1992,61],[1993,42],[1994,76],[1995,61],[1996,39],[1997,59],[1998,53],[1999,50],[2000,59]],"total": 178153,"name": " Queueing Syst. " },
{"articles":[[1999,25],[2000,26]],"total": 178204,"name": " RAIRO - Operations Research " },
{"articles":[[1990,28],[1991,25],[1992,31],[1993,21],[1994,47],[1995,58],[1996,43],[1997,43],[1998,45],[1999,38],[2000,43]],"total": 178626,"name": " Random Struct. Algorithms " },
{"articles":[[1995,32],[1996,35],[1997,36],[1998,35],[1999,36],[2000,38]],"total": 178838,"name": " Real-Time Imaging " },
{"articles":[[1990,16],[1991,17],[1992,17],[1993,17],[1994,24],[1995,18],[1996,24],[1997,23],[1998,27],[1999,21],[2000,29]],"total": 179071,"name": " Real-Time Systems " },
{"articles":[[2000,106]],"total": 179177,"name": " Rel. Eng. & Sys. Safety " },
{"articles":[[1996,41],[1997,37],[1998,43],[1999,39],[2000,29]],"total": 179366,"name": " Reliable Computing " },
{"articles":[[1991,9],[1992,7],[1993,8],[1994,8],[1995,13],[1996,7],[1997,4],[1998,6],[1999,9],[2000,10]],"total": 179447,"name": " Reports on Mathematical Logic " },
{"articles":[[1996,18],[1997,17],[1998,7],[1999,20],[2000,21]],"total": 179530,"name": " Requir. Eng. " },
{"articles":[[2000,7]],"total": 179537,"name": " Revista Colombiana de Computación " },
{"articles":[[1995,10],[1996,17],[1997,10],[1998,8],[1999,9],[2000,10]],"total": 179601,"name": " RITA " },
{"articles":[[1990,29],[1991,32],[1992,30]],"total": 179692,"name": " Robotersysteme " },
{"articles":[[1990,80],[1991,106],[1992,94],[1993,89],[1994,66],[1995,79],[1996,91],[1997,87],[1998,87],[1999,94],[2000,86]],"total": 180651,"name": " Robotica " },
{"articles":[[1990,27],[1991,51],[1992,43],[1993,27],[1994,40],[1995,65],[1996,86],[1997,94],[1998,70],[1999,82],[2000,83]],"total": 181319,"name": " Robotics and Autonomous Systems " },
{"articles":[[1999,25]],"total": 181344,"name": " Rundbrief der GI-Fachgruppe 5.10 Informationssystem-Architekturen " },
{"articles":[[1998,40],[1999,52],[2000,46]],"total": 181482,"name": " Scalable Computing: Practice and Experience " },
{"articles":[[1992,8],[1993,10],[1994,8],[1995,10],[1996,6],[1998,27],[2000,6]],"total": 181557,"name": " Sci. Ann. Cuza Univ. " },
{"articles":[[1990,29],[1991,14],[1992,19],[1993,20],[1994,26],[1995,22],[1996,30],[1997,26],[1998,31],[1999,23],[2000,32]],"total": 181829,"name": " Sci. Comput. Program. " },
{"articles":[[1992,21],[1993,20],[1994,21],[1995,19],[1996,25],[1997,22],[1999,24],[2000,14]],"total": 181995,"name": " Scientific Programming " },
{"articles":[[1990,71],[1991,83],[1992,84],[1993,61],[1994,95],[1995,83],[1996,97],[1997,79],[1998,89],[1999,139],[2000,87]],"total": 182963,"name": " Scientometrics " },
{"articles":[[1990,77],[1991,72],[1992,71],[1993,81],[1994,79],[1995,78],[1996,62],[1997,84],[1998,130],[1999,115],[2000,135]],"total": 183947,"name": " SIAM J. Comput. " },
{"articles":[[1999,17],[2000,150]],"total": 184114,"name": " SIAM J. Control and Optimization " },
{"articles":[[1990,52],[1991,51],[1992,49],[1993,51],[1994,64],[1995,43],[1996,49],[1997,46],[1998,47],[1999,39],[2000,38]],"total": 184643,"name": " SIAM J. Discrete Math. " },
{"articles":[[1999,10],[2000,96]],"total": 184749,"name": " SIAM J. Math. Analysis " },
{"articles":[[1999,21],[2000,110]],"total": 184880,"name": " SIAM J. Matrix Analysis Applications " },
{"articles":[[2000,83]],"total": 184963,"name": " SIAM J. Numerical Analysis " },
{"articles":[[1990,69],[1991,82],[1992,85],[1993,86],[1994,91],[1995,86],[1996,91],[1997,95],[1998,166],[1999,140],[2000,110]],"total": 186064,"name": " SIAM J. Scientific Computing " },
{"articles":[[1995,91],[1996,76],[1997,77],[1998,149],[1999,71],[2000,123]],"total": 186651,"name": " SIAM Journal of Applied Mathematics " },
{"articles":[[1991,38],[1992,34],[1993,47],[1994,51],[1995,43],[1996,61],[1997,62],[1998,73],[1999,62],[2000,78]],"total": 187200,"name": " SIAM Journal on Optimization " },
{"articles":[[1990,154],[1991,165],[1992,148],[1993,169],[1994,168],[1995,146],[1996,143],[1997,45],[1998,70],[1999,50],[2000,46]],"total": 188504,"name": " SIAM Review " },
{"articles":[[1990,32],[1991,36],[1992,32],[1993,39],[1994,37],[1995,43],[1996,49],[1997,58],[1998,57],[1999,58],[2000,64]],"total": 189009,"name": " Sig. Proc.: Image Comm. " },
{"articles":[[1990,21],[1994,28],[1995,45],[1996,32],[1997,44],[1998,41],[1999,46],[2000,50]],"total": 189316,"name": " SIGACT News " },
{"articles":[[1999,27],[2000,14]],"total": 189357,"name": " SIGARCH Computer Architecture News " },
{"articles":[[1990,8],[1991,66],[1992,5],[1993,6],[1994,13],[1995,21],[1996,13],[1997,7],[1998,25]],"total": 189521,"name": " SIGART Bulletin " },
{"articles":[[1997,33],[1998,50],[1999,64],[2000,55]],"total": 189723,"name": " SIGCSE Bulletin " },
{"articles":[[2000,6]],"total": 189729,"name": " SIGecom Exchanges " },
{"articles":[[1990,22],[1991,19],[1992,16],[1993,17],[1994,13],[1995,13],[1996,14],[1997,20],[1998,15],[1999,21],[2000,8]],"total": 189907,"name": " SIGIR Forum " },
{"articles":[[1999,12],[2000,61]],"total": 189980,"name": " SIGKDD Explorations " },
{"articles":[[1990,15],[1991,16],[1992,21],[1993,8],[1995,5],[1997,10],[1998,21],[1999,24],[2000,24]],"total": 190124,"name": " SIGMETRICS Performance Evaluation Review " },
{"articles":[[1990,46],[1991,47],[1992,51],[1993,50],[1994,50],[1995,56],[1996,54],[1997,43],[1998,49],[1999,51],[2000,47]],"total": 190668,"name": " SIGMOD Record " },
{"articles":[[1997,213],[1998,195],[1999,200],[2000,201]],"total": 191477,"name": " Signal Processing " },
{"articles":[[1990,78],[1991,66],[1992,81],[1993,59],[1994,79],[1995,53],[1996,75],[1997,66],[1998,78],[1999,44],[2000,49]],"total": 192205,"name": " SIGPLAN Notices " },
{"articles":[[1993,11],[1994,16],[1995,24],[1996,30],[1997,45],[1998,44],[1999,35],[2000,30]],"total": 192440,"name": " Simul. Pr. Theory " },
{"articles":[[1996,80],[1997,66],[1998,87],[1999,94],[2000,71]],"total": 192838,"name": " Simulation " },
{"articles":[[2000,45]],"total": 192883,"name": " Social Choice and Welfare " },
{"articles":[[1999,14],[2000,25]],"total": 192922,"name": " Social Networks " },
{"articles":[[1997,21],[1998,31],[1999,27],[2000,35]],"total": 193036,"name": " Soft Comput. " },
{"articles":[[1990,82],[1991,70],[1992,52],[1993,69],[1994,59],[1995,68],[1996,68],[1997,70],[1998,68],[1999,69],[2000,67]],"total": 193778,"name": " Softw.  Pract. Exper. " },
{"articles":[[1991,21],[1992,30],[1993,15],[1994,23],[1995,19],[1996,14],[1997,21],[1998,20],[1999,23],[2000,19]],"total": 193983,"name": " Softw. Test.  Verif. Reliab. " },
{"articles":[[1994,15],[1995,18],[1996,17],[1997,16],[1998,18],[2000,7]],"total": 194074,"name": " Software - Concepts and Tools " },
{"articles":[[1997,27]],"total": 194101,"name": " Software Engineering - IEE Proceedings " },
{"articles":[[1990,36],[1991,41],[1992,42],[1993,31],[1994,27],[1995,26],[1996,36]],"total": 194340,"name": " Software Engineering Journal " },
{"articles":[[2000,8]],"total": 194348,"name": " Software Focus " },
{"articles":[[1995,7],[1997,26],[1998,20],[2000,21]],"total": 194422,"name": " Software Process: Improvement and Practice " },
{"articles":[[1995,25],[1996,29],[1997,25],[1998,21],[1999,24]],"total": 194546,"name": " Software Quality Journal " },
{"articles":[[2000,57]],"total": 194603,"name": " Softwaretechnik-Trends " },
{"articles":[[2000,36]],"total": 194639,"name": " South African Computer Journal " },
{"articles":[[1997,5],[1998,16],[1999,6],[2000,23]],"total": 194689,"name": " Space Communications " },
{"articles":[[1999,23],[2000,19]],"total": 194731,"name": " Spatial Cognition & Computation " },
{"articles":[[1990,59],[1991,43],[1992,54],[1993,76],[1994,52],[1995,47],[1996,75],[1997,67],[1998,53],[1999,56],[2000,69]],"total": 195382,"name": " Speech Communication " },
{"articles":[[1997,29],[1998,31],[1999,45],[2000,30]],"total": 195517,"name": " Statistics and Computing " },
{"articles":[[1990,16],[1991,17],[1992,16],[1993,17]],"total": 195583,"name": " Structured Programming " },
{"articles":[[1997,12],[1998,16],[1999,9],[2000,16]],"total": 195636,"name": " STTT " },
{"articles":[[1992,24],[1993,31],[1994,31],[1995,35],[1996,41],[1997,37],[1998,39],[1999,38],[2000,59]],"total": 195971,"name": " Studia Logica " },
{"articles":[[1997,1]],"total": 195972,"name": " submitted to IEEE Expert " },
{"articles":[[1999,38],[2000,79]],"total": 196089,"name": " Synthese " },
{"articles":[[1990,121],[1991,132],[1992,126],[1993,83],[1994,104],[1995,132],[1996,119],[1997,124],[1998,109],[1999,122],[2000,139]],"total": 197400,"name": " Systems and Computers in Japan " },
{"articles":[[1996,24],[1997,22],[1999,29],[2000,23]],"total": 197498,"name": " T. GIS " },
{"articles":[[1995,18],[1996,20],[1997,18],[1998,19],[1999,22]],"total": 197595,"name": " TAPOS " },
{"articles":[[1996,1]],"total": 197596,"name": " technical Report 248  ETH Zürich  Dept. of Computer Science " },
{"articles":[[1993,39],[1994,18],[1995,22],[1996,46],[1997,39],[1998,44],[1999,44],[2000,71]],"total": 197919,"name": " Telecommunication Systems " },
{"articles":[[1998,18],[1999,13],[2000,11]],"total": 197961,"name": " Telematics and Informatics " },
{"articles":[[2000,284]],"total": 198245,"name": " The American Mathematical Monthly " },
{"articles":[[1999,28],[2000,31]],"total": 198304,"name": " The Electronic Library " },
{"articles":[[1990,14],[1991,15],[1992,21],[1993,14],[1994,11],[1995,25],[1996,12],[1997,26],[1998,19],[1999,28],[2000,45]],"total": 198534,"name": " The Journal of Supercomputing " },
{"articles":[[1995,12],[1996,11],[1997,11],[1998,13],[1999,10],[2000,8]],"total": 198599,"name": " The New Review of Hypermedia and Multimedia " },
{"articles":[[1990,33],[1991,34],[1992,38],[1993,42],[1994,27],[1995,35],[1996,42],[1997,27],[1998,39],[1999,40],[2000,37]],"total": 198993,"name": " The Visual Computer " },
{"articles":[[1990,141],[1991,251],[1992,245],[1993,239],[1994,280],[1995,227],[1996,278],[1997,283],[1998,266],[1999,253],[2000,317]],"total": 201773,"name": " Theor. Comput. Sci. " },
{"articles":[[1997,33],[1998,35],[1999,26],[2000,22]],"total": 201889,"name": " Theory Comput. Syst. " },
{"articles":[[2000,21]],"total": 201910,"name": " Theory in Biosciences " },
{"articles":[[1999,20],[2000,21]],"total": 201951,"name": " Transactions of the SDPS " },
{"articles":[[1995,29],[1996,29],[1997,33],[1998,28],[1999,30],[2000,30]],"total": 202130,"name": " Transportation Science " },
{"articles":[[1992,28],[1993,24],[1994,18],[1995,24],[1996,45],[1997,27],[1998,30],[1999,29],[2000,13]],"total": 202368,"name": " Universität Trier  Mathematik/Informatik  Forschungsbericht " },
{"articles":[[1991,11],[1992,12],[1993,9],[1994,5],[1995,19],[1996,10],[1997,14],[1998,13],[1999,10],[2000,12]],"total": 202483,"name": " User Model. User-Adapt. Interact. " },
{"articles":[[1995,15],[1996,5],[1998,27],[1999,26],[2000,24]],"total": 202580,"name": " Virtual Reality " },
{"articles":[[1992,9],[1993,19],[1994,21],[1995,23],[1996,18],[1997,20],[1998,20],[1999,8],[2000,27]],"total": 202745,"name": " VLDB J. " },
{"articles":[[1990,27],[1991,36],[1992,26],[1993,47],[1994,43],[1995,50],[1996,58],[1997,54],[1998,60],[1999,62],[2000,58]],"total": 203266,"name": " VLSI Signal Processing " },
{"articles":[[1995,38],[1996,31],[1997,45],[1998,46],[1999,41],[2000,42]],"total": 203509,"name": " Wireless Networks " },
{"articles":[[1994,25],[1995,25],[1996,28],[1997,35],[1998,55],[1999,50],[2000,68]],"total": 203795,"name": " Wireless Personal Communications " },
{"articles":[[1990,55],[1991,62],[1992,61],[1993,55],[1994,55],[1995,62],[1996,73],[1997,70],[1998,65],[1999,69],[2000,95]],"total": 204517,"name": " Wirtschaftsinformatik " },
{"articles":[[1998,20],[1999,17],[2000,21]],"total": 204575,"name": " World Wide Web " },
{"articles":[[1997,21]],"total": 204596,"name": " World Wide Web Journal " }]